Workbook

Sheet Akun
A1: ID Anggota | B1: Email | C1: PIN | D1: Status PIN | E1: Role | F1: Status Akun
A2: DBP00000000 | B2: halo.ikadbp@gmail.com | C2: 111111 | D2: Default | E2: Anggota | F2: Aktif
A3: =IFERROR(__xludf.DUMMYFUNCTION("QUERY(Database!A3:G2003,""Select A,G"",)"),"DBP01000001") -> DBP01000001 | B3: =IFERROR(__xludf.DUMMYFUNCTION("""COMPUTED_VALUE"""),"akbar.lawyer85@gmail.com") -> akbar.lawyer85@gmail.com | C3: 260185 | D3: Changed | E3: Anggota | F3: Aktif
A4: =IFERROR(__xludf.DUMMYFUNCTION("""COMPUTED_VALUE"""),"DBP01000002") -> DBP01000002 | B4: =IFERROR(__xludf.DUMMYFUNCTION("""COMPUTED_VALUE"""),"avgoenadi@gmail.com") -> avgoenadi@gmail.com | C4: 112233 | D4: Changed | E4: Anggota | F4: Aktif
A5: =IFERROR(__xludf.DUMMYFUNCTION("""COMPUTED_VALUE"""),"DBP01000003") -> DBP01000003 | B5: =IFERROR(__xludf.DUMMYFUNCTION("""COMPUTED_VALUE"""),"gema.kusumaputri@gmail.com") -> gema.kusumaputri@gmail.com | C5: 123123 | D5: Default | E5: Anggota | F5: Aktif
A6: =IFERROR(__xludf.DUMMYFUNCTION("""COMPUTED_VALUE"""),"DBP01000004") -> DBP01000004 | B6: =IFERROR(__xludf.DUMMYFUNCTION("""COMPUTED_VALUE"""),"putuagnia@gmail.com") -> putuagnia@gmail.com | C6: 123123 | D6: Default | E6: Anggota | F6: Aktif
A7: =IFERROR(__xludf.DUMMYFUNCTION("""COMPUTED_VALUE"""),"DBP01000005") -> DBP01000005 | B7: =IFERROR(__xludf.DUMMYFUNCTION("""COMPUTED_VALUE"""),"dante.darmawangsa@upi.edu") -> dante.darmawangsa@upi.edu | C7: 123123 | D7: Default | E7: Anggota | F7: Aktif
A8: =IFERROR(__xludf.DUMMYFUNCTION("""COMPUTED_VALUE"""),"DBP01000006") -> DBP01000006 | B8: =IFERROR(__xludf.DUMMYFUNCTION("""COMPUTED_VALUE"""),"ratri.mustikaning.h@gmail.com") -> ratri.mustikaning.h@gmail.com | C8: 123123 | D8: Default | E8: Anggota | F8: Aktif
A9: =IFERROR(__xludf.DUMMYFUNCTION("""COMPUTED_VALUE"""),"DBP01000007") -> DBP01000007 | B9: =IFERROR(__xludf.DUMMYFUNCTION("""COMPUTED_VALUE"""),"puti.kemala.tanjung@gmail.com") -> puti.kemala.tanjung@gmail.com | C9: 123123 | D9: Default | E9: Anggota | F9: Aktif
A10: =IFERROR(__xludf.DUMMYFUNCTION("""COMPUTED_VALUE"""),"DBP01000008") -> DBP01000008 | B10: =IFERROR(__xludf.DUMMYFUNCTION("""COMPUTED_VALUE"""),"roroajengtaufik@gmail.com") -> roroajengtaufik@gmail.com | C10: 123123 | D10: Default | E10: Anggota | F10: Aktif
A11: =IFERROR(__xludf.DUMMYFUNCTION("""COMPUTED_VALUE"""),"DBP01000009") -> DBP01000009 | B11: =IFERROR(__xludf.DUMMYFUNCTION("""COMPUTED_VALUE"""),"wayqodratulloh@gmail.com") -> wayqodratulloh@gmail.com | C11: 123123 | D11: Default | E11: Anggota | F11: Aktif
A12: =IFERROR(__xludf.DUMMYFUNCTION("""COMPUTED_VALUE"""),"DBP01000010") -> DBP01000010 | B12: =IFERROR(__xludf.DUMMYFUNCTION("""COMPUTED_VALUE"""),"gp.handoko15@gmail.com") -> gp.handoko15@gmail.com | C12: 123123 | D12: Default | E12: Anggota | F12: Aktif
A13: =IFERROR(__xludf.DUMMYFUNCTION("""COMPUTED_VALUE"""),"DBP01000011") -> DBP01000011 | B13: =IFERROR(__xludf.DUMMYFUNCTION("""COMPUTED_VALUE"""),"doddyfirman@yahoo.com") -> doddyfirman@yahoo.com | C13: 123123 | D13: Default | E13: Anggota | F13: Aktif
A14: =IFERROR(__xludf.DUMMYFUNCTION("""COMPUTED_VALUE"""),"DBP01000012") -> DBP01000012 | B14: =IFERROR(__xludf.DUMMYFUNCTION("""COMPUTED_VALUE"""),"hawitguritno@gmail.com") -> hawitguritno@gmail.com | C14: 123123 | D14: Default | E14: Anggota | F14: Aktif
A15: =IFERROR(__xludf.DUMMYFUNCTION("""COMPUTED_VALUE"""),"DBP01000013") -> DBP01000013 | B15: =IFERROR(__xludf.DUMMYFUNCTION("""COMPUTED_VALUE"""),"malaekayanti@gmail.com") -> malaekayanti@gmail.com | C15: 123123 | D15: Default | E15: Anggota | F15: Aktif
A16: =IFERROR(__xludf.DUMMYFUNCTION("""COMPUTED_VALUE"""),"DBP01000014") -> DBP01000014 | B16: =IFERROR(__xludf.DUMMYFUNCTION("""COMPUTED_VALUE"""),"rizkiarisy@gmail.com") -> rizkiarisy@gmail.com | C16: 123123 | D16: Default | E16: Anggota | F16: Aktif
A17: =IFERROR(__xludf.DUMMYFUNCTION("""COMPUTED_VALUE"""),"DBP01000015") -> DBP01000015 | B17: =IFERROR(__xludf.DUMMYFUNCTION("""COMPUTED_VALUE"""),"fazia.febriany@gmail.com") -> fazia.febriany@gmail.com | C17: 123123 | D17: Default | E17: Anggota | F17: Aktif
A18: =IFERROR(__xludf.DUMMYFUNCTION("""COMPUTED_VALUE"""),"DBP01000016") -> DBP01000016 | B18: =IFERROR(__xludf.DUMMYFUNCTION("""COMPUTED_VALUE"""),"wijayajilan@gmail.com") -> wijayajilan@gmail.com | C18: 123123 | D18: Default | E18: Anggota | F18: Aktif
A19: =IFERROR(__xludf.DUMMYFUNCTION("""COMPUTED_VALUE"""),"DBP01000017") -> DBP01000017 | B19: =IFERROR(__xludf.DUMMYFUNCTION("""COMPUTED_VALUE"""),"nurrohmanazis1992@gmail.com") -> nurrohmanazis1992@gmail.com | C19: 123123 | D19: Default | E19: Anggota | F19: Aktif
A20: =IFERROR(__xludf.DUMMYFUNCTION("""COMPUTED_VALUE"""),"DBP01000018") -> DBP01000018 | C20: 123123 | D20: Default | E20: Anggota | F20: Aktif
A21: =IFERROR(__xludf.DUMMYFUNCTION("""COMPUTED_VALUE"""),"DBP01000019") -> DBP01000019 | B21: =IFERROR(__xludf.DUMMYFUNCTION("""COMPUTED_VALUE"""),"nicho.tarigan@gmail.com") -> nicho.tarigan@gmail.com | C21: 123123 | D21: Default | E21: Anggota | F21: Aktif
A22: =IFERROR(__xludf.DUMMYFUNCTION("""COMPUTED_VALUE"""),"DBP01000020") -> DBP01000020 | B22: =IFERROR(__xludf.DUMMYFUNCTION("""COMPUTED_VALUE"""),"Ogyfabrio@gmail.com") -> Ogyfabrio@gmail.com | C22: 123123 | D22: Default | E22: Anggota | F22: Aktif
A23: =IFERROR(__xludf.DUMMYFUNCTION("""COMPUTED_VALUE"""),"DBP01000021") -> DBP01000021 | B23: =IFERROR(__xludf.DUMMYFUNCTION("""COMPUTED_VALUE"""),"suhandies@gmail.com") -> suhandies@gmail.com | C23: 123123 | D23: Default | E23: Anggota | F23: Aktif
A24: =IFERROR(__xludf.DUMMYFUNCTION("""COMPUTED_VALUE"""),"DBP01000022") -> DBP01000022 | B24: =IFERROR(__xludf.DUMMYFUNCTION("""COMPUTED_VALUE"""),"riyadhi.atha@gmail.com") -> riyadhi.atha@gmail.com | C24: 123123 | D24: Default | E24: Anggota | F24: Aktif
A25: =IFERROR(__xludf.DUMMYFUNCTION("""COMPUTED_VALUE"""),"DBP01000023") -> DBP01000023 | B25: =IFERROR(__xludf.DUMMYFUNCTION("""COMPUTED_VALUE"""),"Marthanitaflorentinas@gmail.com") -> Marthanitaflorentinas@gmail.com | C25: 123123 | D25: Default | E25: Anggota | F25: Aktif
A26: =IFERROR(__xludf.DUMMYFUNCTION("""COMPUTED_VALUE"""),"DBP01000024") -> DBP01000024 | B26: =IFERROR(__xludf.DUMMYFUNCTION("""COMPUTED_VALUE"""),"ferdinand.hiu@gmail.com") -> ferdinand.hiu@gmail.com | C26: 123123 | D26: Default | E26: Anggota | F26: Aktif
A27: =IFERROR(__xludf.DUMMYFUNCTION("""COMPUTED_VALUE"""),"DBP01000025") -> DBP01000025 | B27: =IFERROR(__xludf.DUMMYFUNCTION("""COMPUTED_VALUE"""),"sagitas@xlfutureleaders.com") -> sagitas@xlfutureleaders.com | C27: 123123 | D27: Default | E27: Anggota | F27: Aktif
A28: =IFERROR(__xludf.DUMMYFUNCTION("""COMPUTED_VALUE"""),"DBP01000026") -> DBP01000026 | B28: =IFERROR(__xludf.DUMMYFUNCTION("""COMPUTED_VALUE"""),"herozh94@gmail.com") -> herozh94@gmail.com | C28: 123123 | D28: Default | E28: Anggota | F28: Aktif
A29: =IFERROR(__xludf.DUMMYFUNCTION("""COMPUTED_VALUE"""),"DBP01000027") -> DBP01000027 | B29: =IFERROR(__xludf.DUMMYFUNCTION("""COMPUTED_VALUE"""),"Fjrhdy11@gmail.com") -> Fjrhdy11@gmail.com | C29: 123123 | D29: Default | E29: Anggota | F29: Aktif
A30: =IFERROR(__xludf.DUMMYFUNCTION("""COMPUTED_VALUE"""),"DBP01000028") -> DBP01000028 | B30: =IFERROR(__xludf.DUMMYFUNCTION("""COMPUTED_VALUE"""),"khasanm86@gmail.com") -> khasanm86@gmail.com | C30: 123123 | D30: Default | E30: Anggota | F30: Aktif
A31: =IFERROR(__xludf.DUMMYFUNCTION("""COMPUTED_VALUE"""),"DBP01000029") -> DBP01000029 | B31: =IFERROR(__xludf.DUMMYFUNCTION("""COMPUTED_VALUE"""),"ilham.pbd@gmail.com") -> ilham.pbd@gmail.com | C31: 30419 | D31: Changed | E31: Anggota | F31: Aktif
A32: =IFERROR(__xludf.DUMMYFUNCTION("""COMPUTED_VALUE"""),"DBP01000030") -> DBP01000030 | B32: =IFERROR(__xludf.DUMMYFUNCTION("""COMPUTED_VALUE"""),"shafi.faris33@gmail.com") -> shafi.faris33@gmail.com | C32: 123123 | D32: Default | E32: Anggota | F32: Aktif
A33: =IFERROR(__xludf.DUMMYFUNCTION("""COMPUTED_VALUE"""),"DBP01000031") -> DBP01000031 | B33: =IFERROR(__xludf.DUMMYFUNCTION("""COMPUTED_VALUE"""),"Hapinksihanti89@gmail.com ") -> Hapinksihanti89@gmail.com | C33: 123123 | D33: Default | E33: Anggota | F33: Aktif
A34: =IFERROR(__xludf.DUMMYFUNCTION("""COMPUTED_VALUE"""),"DBP01000032") -> DBP01000032 | B34: =IFERROR(__xludf.DUMMYFUNCTION("""COMPUTED_VALUE"""),"didopranata@gmail.com") -> didopranata@gmail.com | C34: 123123 | D34: Default | E34: Anggota | F34: Aktif
A35: =IFERROR(__xludf.DUMMYFUNCTION("""COMPUTED_VALUE"""),"DBP01000033") -> DBP01000033 | B35: =IFERROR(__xludf.DUMMYFUNCTION("""COMPUTED_VALUE"""),"putununiek89@unhi.ac.id") -> putununiek89@unhi.ac.id | C35: 123123 | D35: Default | E35: Anggota | F35: Aktif
A36: =IFERROR(__xludf.DUMMYFUNCTION("""COMPUTED_VALUE"""),"DBP01000034") -> DBP01000034 | B36: =IFERROR(__xludf.DUMMYFUNCTION("""COMPUTED_VALUE"""),"neserike@gmail.com") -> neserike@gmail.com | C36: 123123 | D36: Default | E36: Anggota | F36: Aktif
A37: =IFERROR(__xludf.DUMMYFUNCTION("""COMPUTED_VALUE"""),"DBP01000035") -> DBP01000035 | B37: =IFERROR(__xludf.DUMMYFUNCTION("""COMPUTED_VALUE"""),"yudith.tm@gmail.com") -> yudith.tm@gmail.com | C37: 123123 | D37: Default | E37: Anggota | F37: Aktif
A38: =IFERROR(__xludf.DUMMYFUNCTION("""COMPUTED_VALUE"""),"DBP01000036") -> DBP01000036 | C38: 123123 | D38: Default | E38: Anggota | F38: Aktif
A39: =IFERROR(__xludf.DUMMYFUNCTION("""COMPUTED_VALUE"""),"DBP01000037") -> DBP01000037 | B39: =IFERROR(__xludf.DUMMYFUNCTION("""COMPUTED_VALUE"""),"deidranataliet@gmail.com") -> deidranataliet@gmail.com | C39: 123123 | D39: Default | E39: Anggota | F39: Aktif
A40: =IFERROR(__xludf.DUMMYFUNCTION("""COMPUTED_VALUE"""),"DBP01000038") -> DBP01000038 | B40: =IFERROR(__xludf.DUMMYFUNCTION("""COMPUTED_VALUE"""),"dianboer@gmail.com") -> dianboer@gmail.com | C40: 123123 | D40: Default | E40: Anggota | F40: Aktif
A41: =IFERROR(__xludf.DUMMYFUNCTION("""COMPUTED_VALUE"""),"DBP01000039") -> DBP01000039 | B41: =IFERROR(__xludf.DUMMYFUNCTION("""COMPUTED_VALUE"""),"pelitawati1@gmail.com") -> pelitawati1@gmail.com | C41: 123123 | D41: Default | E41: Anggota | F41: Aktif
A42: =IFERROR(__xludf.DUMMYFUNCTION("""COMPUTED_VALUE"""),"DBP01000040") -> DBP01000040 | B42: =IFERROR(__xludf.DUMMYFUNCTION("""COMPUTED_VALUE"""),"ricohalim46@gmail.com") -> ricohalim46@gmail.com | C42: 112233 | D42: Changed | E42: Anggota | F42: Aktif
A43: =IFERROR(__xludf.DUMMYFUNCTION("""COMPUTED_VALUE"""),"DBP01000041") -> DBP01000041 | B43: =IFERROR(__xludf.DUMMYFUNCTION("""COMPUTED_VALUE"""),"citra.asmara.83@gmail.com") -> citra.asmara.83@gmail.com | C43: 123123 | D43: Default | E43: Anggota | F43: Aktif
A44: =IFERROR(__xludf.DUMMYFUNCTION("""COMPUTED_VALUE"""),"DBP01000042") -> DBP01000042 | B44: =IFERROR(__xludf.DUMMYFUNCTION("""COMPUTED_VALUE"""),"cynthiakp.ckp@gmail.com") -> cynthiakp.ckp@gmail.com | C44: 123123 | D44: Default | E44: Anggota | F44: Aktif
A45: =IFERROR(__xludf.DUMMYFUNCTION("""COMPUTED_VALUE"""),"DBP01000043") -> DBP01000043 | B45: =IFERROR(__xludf.DUMMYFUNCTION("""COMPUTED_VALUE"""),"solehrifai@gmail.com") -> solehrifai@gmail.com | C45: 123123 | D45: Default | E45: Anggota | F45: Aktif
A46: =IFERROR(__xludf.DUMMYFUNCTION("""COMPUTED_VALUE"""),"DBP01000044") -> DBP01000044 | B46: =IFERROR(__xludf.DUMMYFUNCTION("""COMPUTED_VALUE"""),"iqbalfa5@gmail.com") -> iqbalfa5@gmail.com | C46: 959089 | D46: Changed | E46: Anggota | F46: Aktif
A47: =IFERROR(__xludf.DUMMYFUNCTION("""COMPUTED_VALUE"""),"DBP01000045") -> DBP01000045 | B47: =IFERROR(__xludf.DUMMYFUNCTION("""COMPUTED_VALUE"""),"nisalatu1995@gmail.com") -> nisalatu1995@gmail.com | C47: 123123 | D47: Default | E47: Anggota | F47: Aktif
A48: =IFERROR(__xludf.DUMMYFUNCTION("""COMPUTED_VALUE"""),"DBP01000046") -> DBP01000046 | B48: =IFERROR(__xludf.DUMMYFUNCTION("""COMPUTED_VALUE"""),"faizaldikky@gmail.com") -> faizaldikky@gmail.com | C48: 123123 | D48: Default | E48: Anggota | F48: Aktif
A49: =IFERROR(__xludf.DUMMYFUNCTION("""COMPUTED_VALUE"""),"DBP01000047") -> DBP01000047 | B49: =IFERROR(__xludf.DUMMYFUNCTION("""COMPUTED_VALUE"""),"veronicamdn9@gmail.com") -> veronicamdn9@gmail.com | C49: User123456 | D49: Changed | E49: Anggota | F49: Aktif
A50: =IFERROR(__xludf.DUMMYFUNCTION("""COMPUTED_VALUE"""),"DBP01000048") -> DBP01000048 | B50: =IFERROR(__xludf.DUMMYFUNCTION("""COMPUTED_VALUE"""),"rikarahmayuni08@gmail.com") -> rikarahmayuni08@gmail.com | C50: 123123 | D50: Default | E50: Anggota | F50: Aktif
A51: =IFERROR(__xludf.DUMMYFUNCTION("""COMPUTED_VALUE"""),"DBP01000049") -> DBP01000049 | C51: 123123 | D51: Default | E51: Anggota | F51: Aktif
A52: =IFERROR(__xludf.DUMMYFUNCTION("""COMPUTED_VALUE"""),"DBP01000050") -> DBP01000050 | B52: =IFERROR(__xludf.DUMMYFUNCTION("""COMPUTED_VALUE"""),"pandusukmaks@gmail.com") -> pandusukmaks@gmail.com | C52: 123123 | D52: Default | E52: Anggota | F52: Aktif
A53: =IFERROR(__xludf.DUMMYFUNCTION("""COMPUTED_VALUE"""),"DBP01000051") -> DBP01000051 | B53: =IFERROR(__xludf.DUMMYFUNCTION("""COMPUTED_VALUE"""),"yukaprm29@gmail.com") -> yukaprm29@gmail.com | C53: 123123 | D53: Default | E53: Anggota | F53: Aktif
A54: =IFERROR(__xludf.DUMMYFUNCTION("""COMPUTED_VALUE"""),"DBP01000052") -> DBP01000052 | B54: =IFERROR(__xludf.DUMMYFUNCTION("""COMPUTED_VALUE"""),"dudih.sutrisman@yahoo.co.id") -> dudih.sutrisman@yahoo.co.id | C54: 123123 | D54: Default | E54: Anggota | F54: Aktif
A55: =IFERROR(__xludf.DUMMYFUNCTION("""COMPUTED_VALUE"""),"DBP01000053") -> DBP01000053 | B55: =IFERROR(__xludf.DUMMYFUNCTION("""COMPUTED_VALUE"""),"baguz87@gmail.com") -> baguz87@gmail.com | C55: 123123 | D55: Default | E55: Anggota | F55: Aktif
A56: =IFERROR(__xludf.DUMMYFUNCTION("""COMPUTED_VALUE"""),"DBP01000054") -> DBP01000054 | B56: =IFERROR(__xludf.DUMMYFUNCTION("""COMPUTED_VALUE"""),"andreseptian227@gmail.com") -> andreseptian227@gmail.com | C56: 123123 | D56: Default | E56: Anggota | F56: Aktif
A57: =IFERROR(__xludf.DUMMYFUNCTION("""COMPUTED_VALUE"""),"DBP01000055") -> DBP01000055 | B57: =IFERROR(__xludf.DUMMYFUNCTION("""COMPUTED_VALUE"""),"uswachassanah@gmail.com") -> uswachassanah@gmail.com | C57: 123123 | D57: Default | E57: Anggota | F57: Aktif
A58: =IFERROR(__xludf.DUMMYFUNCTION("""COMPUTED_VALUE"""),"DBP01000056") -> DBP01000056 | B58: =IFERROR(__xludf.DUMMYFUNCTION("""COMPUTED_VALUE"""),"akbar.bayurahmat@gmail.com") -> akbar.bayurahmat@gmail.com | C58: 123123 | D58: Default | E58: Anggota | F58: Aktif
A59: =IFERROR(__xludf.DUMMYFUNCTION("""COMPUTED_VALUE"""),"DBP01000057") -> DBP01000057 | B59: =IFERROR(__xludf.DUMMYFUNCTION("""COMPUTED_VALUE"""),"Fitraarrahma12@gmail.com") -> Fitraarrahma12@gmail.com | C59: 123123 | D59: Default | E59: Anggota | F59: Aktif
A60: =IFERROR(__xludf.DUMMYFUNCTION("""COMPUTED_VALUE"""),"DBP01000058") -> DBP01000058 | B60: =IFERROR(__xludf.DUMMYFUNCTION("""COMPUTED_VALUE"""),"nidya.hendrawan.tjong@gmail.com") -> nidya.hendrawan.tjong@gmail.com | C60: 123123 | D60: Default | E60: Anggota | F60: Aktif
A61: =IFERROR(__xludf.DUMMYFUNCTION("""COMPUTED_VALUE"""),"DBP01000059") -> DBP01000059 | B61: =IFERROR(__xludf.DUMMYFUNCTION("""COMPUTED_VALUE"""),"ameliaaugustin00@gmail.com") -> ameliaaugustin00@gmail.com | C61: 123123 | D61: Default | E61: Anggota | F61: Aktif
A62: =IFERROR(__xludf.DUMMYFUNCTION("""COMPUTED_VALUE"""),"DBP01000060") -> DBP01000060 | B62: =IFERROR(__xludf.DUMMYFUNCTION("""COMPUTED_VALUE"""),"farid.noor@umk.ac.id") -> farid.noor@umk.ac.id | C62: 123123 | D62: Default | E62: Anggota | F62: Aktif
A63: =IFERROR(__xludf.DUMMYFUNCTION("""COMPUTED_VALUE"""),"DBP01000061") -> DBP01000061 | B63: =IFERROR(__xludf.DUMMYFUNCTION("""COMPUTED_VALUE"""),"shapangestu@gmail.com") -> shapangestu@gmail.com | C63: 123123 | D63: Default | E63: Anggota | F63: Aktif
A64: =IFERROR(__xludf.DUMMYFUNCTION("""COMPUTED_VALUE"""),"DBP01000062") -> DBP01000062 | B64: =IFERROR(__xludf.DUMMYFUNCTION("""COMPUTED_VALUE"""),"ikarezvaniaprita@gmail.com") -> ikarezvaniaprita@gmail.com | C64: 123123 | D64: Default | E64: Anggota | F64: Aktif
A65: =IFERROR(__xludf.DUMMYFUNCTION("""COMPUTED_VALUE"""),"DBP01000063") -> DBP01000063 | B65: =IFERROR(__xludf.DUMMYFUNCTION("""COMPUTED_VALUE"""),"Ikrimahtaufikhidayat@gmail.com") -> Ikrimahtaufikhidayat@gmail.com | C65: 123123 | D65: Default | E65: Anggota | F65: Aktif
A66: =IFERROR(__xludf.DUMMYFUNCTION("""COMPUTED_VALUE"""),"DBP01000064") -> DBP01000064 | B66: =IFERROR(__xludf.DUMMYFUNCTION("""COMPUTED_VALUE"""),"Sasrisyapin@gmail.com") -> Sasrisyapin@gmail.com | C66: 123123 | D66: Default | E66: Anggota | F66: Aktif
A67: =IFERROR(__xludf.DUMMYFUNCTION("""COMPUTED_VALUE"""),"DBP01000065") -> DBP01000065 | B67: =IFERROR(__xludf.DUMMYFUNCTION("""COMPUTED_VALUE"""),"firmansyahrizal21@gmail.com") -> firmansyahrizal21@gmail.com | C67: 123123 | D67: Default | E67: Anggota | F67: Aktif
A68: =IFERROR(__xludf.DUMMYFUNCTION("""COMPUTED_VALUE"""),"DBP01000066") -> DBP01000066 | B68: =IFERROR(__xludf.DUMMYFUNCTION("""COMPUTED_VALUE"""),"hendi140383@gmail.com ") -> hendi140383@gmail.com | C68: 123123 | D68: Default | E68: Anggota | F68: Aktif
A69: =IFERROR(__xludf.DUMMYFUNCTION("""COMPUTED_VALUE"""),"DBP01000067") -> DBP01000067 | B69: =IFERROR(__xludf.DUMMYFUNCTION("""COMPUTED_VALUE"""),"vixkytanudjaja@gmail.com") -> vixkytanudjaja@gmail.com | C69: 123123 | D69: Default | E69: Anggota | F69: Aktif
A70: =IFERROR(__xludf.DUMMYFUNCTION("""COMPUTED_VALUE"""),"DBP01000068") -> DBP01000068 | B70: =IFERROR(__xludf.DUMMYFUNCTION("""COMPUTED_VALUE"""),"annabelle230413@gmail.com") -> annabelle230413@gmail.com | C70: 123123 | D70: Default | E70: Anggota | F70: Aktif
A71: =IFERROR(__xludf.DUMMYFUNCTION("""COMPUTED_VALUE"""),"DBP01000069") -> DBP01000069 | B71: =IFERROR(__xludf.DUMMYFUNCTION("""COMPUTED_VALUE"""),"denirusmawan826@gmail.com") -> denirusmawan826@gmail.com | C71: 123123 | D71: Default | E71: Anggota | F71: Aktif
A72: =IFERROR(__xludf.DUMMYFUNCTION("""COMPUTED_VALUE"""),"DBP01000070") -> DBP01000070 | C72: 123123 | D72: Default | E72: Anggota | F72: Aktif
A73: =IFERROR(__xludf.DUMMYFUNCTION("""COMPUTED_VALUE"""),"DBP01000071") -> DBP01000071 | B73: =IFERROR(__xludf.DUMMYFUNCTION("""COMPUTED_VALUE"""),"Elisabethevangeline31@gmail.com") -> Elisabethevangeline31@gmail.com | C73: 123123 | D73: Default | E73: Anggota | F73: Aktif
A74: =IFERROR(__xludf.DUMMYFUNCTION("""COMPUTED_VALUE"""),"DBP01000072") -> DBP01000072 | B74: =IFERROR(__xludf.DUMMYFUNCTION("""COMPUTED_VALUE"""),"intanlutviana39@gmail.com") -> intanlutviana39@gmail.com | C74: 123123 | D74: Default | E74: Anggota | F74: Aktif
A75: =IFERROR(__xludf.DUMMYFUNCTION("""COMPUTED_VALUE"""),"DBP01000073") -> DBP01000073 | B75: =IFERROR(__xludf.DUMMYFUNCTION("""COMPUTED_VALUE"""),"annisatalmera@gmail.com") -> annisatalmera@gmail.com | C75: 123123 | D75: Default | E75: Anggota | F75: Aktif
A76: =IFERROR(__xludf.DUMMYFUNCTION("""COMPUTED_VALUE"""),"DBP01000074") -> DBP01000074 | B76: =IFERROR(__xludf.DUMMYFUNCTION("""COMPUTED_VALUE"""),"gabypanglylien@gmail.com") -> gabypanglylien@gmail.com | C76: 123123 | D76: Default | E76: Anggota | F76: Aktif
A77: =IFERROR(__xludf.DUMMYFUNCTION("""COMPUTED_VALUE"""),"DBP01000075") -> DBP01000075 | B77: =IFERROR(__xludf.DUMMYFUNCTION("""COMPUTED_VALUE"""),"Putrasilaban691@gmail.com") -> Putrasilaban691@gmail.com | C77: 123123 | D77: Default | E77: Anggota | F77: Aktif
A78: =IFERROR(__xludf.DUMMYFUNCTION("""COMPUTED_VALUE"""),"DBP01000076") -> DBP01000076 | B78: =IFERROR(__xludf.DUMMYFUNCTION("""COMPUTED_VALUE"""),"suparmanwakidi.s.ak@gmail.com") -> suparmanwakidi.s.ak@gmail.com | C78: 123123 | D78: Default | E78: Anggota | F78: Aktif
A79: =IFERROR(__xludf.DUMMYFUNCTION("""COMPUTED_VALUE"""),"DBP01000077") -> DBP01000077 | B79: =IFERROR(__xludf.DUMMYFUNCTION("""COMPUTED_VALUE"""),"dwipras88@gmail.com") -> dwipras88@gmail.com | C79: 123123 | D79: Default | E79: Anggota | F79: Aktif
A80: =IFERROR(__xludf.DUMMYFUNCTION("""COMPUTED_VALUE"""),"DBP01000078") -> DBP01000078 | B80: =IFERROR(__xludf.DUMMYFUNCTION("""COMPUTED_VALUE"""),"budidennn@gmail.com") -> budidennn@gmail.com | C80: 123123 | D80: Default | E80: Anggota | F80: Aktif
A81: =IFERROR(__xludf.DUMMYFUNCTION("""COMPUTED_VALUE"""),"DBP01000079") -> DBP01000079 | B81: =IFERROR(__xludf.DUMMYFUNCTION("""COMPUTED_VALUE"""),"rizqullahrifqi22@gmail.com") -> rizqullahrifqi22@gmail.com | C81: 123123 | D81: Default | E81: Anggota | F81: Aktif
A82: =IFERROR(__xludf.DUMMYFUNCTION("""COMPUTED_VALUE"""),"DBP02000080") -> DBP02000080 | B82: =IFERROR(__xludf.DUMMYFUNCTION("""COMPUTED_VALUE"""),"adibardianto21@gmail.com") -> adibardianto21@gmail.com | C82: 222222 | D82: Default | E82: Anggota | F82: Aktif
A83: =IFERROR(__xludf.DUMMYFUNCTION("""COMPUTED_VALUE"""),"DBP02000081") -> DBP02000081 | B83: =IFERROR(__xludf.DUMMYFUNCTION("""COMPUTED_VALUE"""),"edwin.setiawan26@gmail.com") -> edwin.setiawan26@gmail.com | C83: 222222 | D83: Default | E83: Anggota | F83: Aktif
A84: =IFERROR(__xludf.DUMMYFUNCTION("""COMPUTED_VALUE"""),"DBP02000082") -> DBP02000082 | B84: =IFERROR(__xludf.DUMMYFUNCTION("""COMPUTED_VALUE"""),"ndawindahayati@gmail.com") -> ndawindahayati@gmail.com | C84: 222222 | D84: Default | E84: Anggota | F84: Aktif
A85: =IFERROR(__xludf.DUMMYFUNCTION("""COMPUTED_VALUE"""),"DBP02000083") -> DBP02000083 | B85: =IFERROR(__xludf.DUMMYFUNCTION("""COMPUTED_VALUE"""),"ikadwiyulita@gmail.com") -> ikadwiyulita@gmail.com | C85: 222222 | D85: Default | E85: Anggota | F85: Aktif
A86: =IFERROR(__xludf.DUMMYFUNCTION("""COMPUTED_VALUE"""),"DBP02000084") -> DBP02000084 | B86: =IFERROR(__xludf.DUMMYFUNCTION("""COMPUTED_VALUE"""),"ekosuhadinata4312@gmail.com") -> ekosuhadinata4312@gmail.com | C86: 222222 | D86: Default | E86: Anggota | F86: Aktif
A87: =IFERROR(__xludf.DUMMYFUNCTION("""COMPUTED_VALUE"""),"DBP02000085") -> DBP02000085 | B87: =IFERROR(__xludf.DUMMYFUNCTION("""COMPUTED_VALUE"""),"wibowoaris297@gmail.com") -> wibowoaris297@gmail.com | C87: 222222 | D87: Default | E87: Anggota | F87: Aktif
A88: =IFERROR(__xludf.DUMMYFUNCTION("""COMPUTED_VALUE"""),"DBP02000086") -> DBP02000086 | B88: =IFERROR(__xludf.DUMMYFUNCTION("""COMPUTED_VALUE"""),"muziebmulyana@gmail.com") -> muziebmulyana@gmail.com | C88: 222222 | D88: Default | E88: Anggota | F88: Aktif
A89: =IFERROR(__xludf.DUMMYFUNCTION("""COMPUTED_VALUE"""),"DBP02000087") -> DBP02000087 | B89: =IFERROR(__xludf.DUMMYFUNCTION("""COMPUTED_VALUE"""),"sabamm31@gmail.com") -> sabamm31@gmail.com | C89: 222222 | D89: Default | E89: Anggota | F89: Aktif
A90: =IFERROR(__xludf.DUMMYFUNCTION("""COMPUTED_VALUE"""),"DBP02000088") -> DBP02000088 | B90: =IFERROR(__xludf.DUMMYFUNCTION("""COMPUTED_VALUE"""),"delidelmonte@gmail.com") -> delidelmonte@gmail.com | C90: 222222 | D90: Default | E90: Anggota | F90: Aktif
A91: =IFERROR(__xludf.DUMMYFUNCTION("""COMPUTED_VALUE"""),"DBP02000089") -> DBP02000089 | B91: =IFERROR(__xludf.DUMMYFUNCTION("""COMPUTED_VALUE"""),"alifyaarahmanita@gmail.com") -> alifyaarahmanita@gmail.com | C91: 222222 | D91: Default | E91: Anggota | F91: Aktif
A92: =IFERROR(__xludf.DUMMYFUNCTION("""COMPUTED_VALUE"""),"DBP02000090") -> DBP02000090 | B92: =IFERROR(__xludf.DUMMYFUNCTION("""COMPUTED_VALUE"""),"hanafakhrani.hf@gmail.com") -> hanafakhrani.hf@gmail.com | C92: 222222 | D92: Default | E92: Anggota | F92: Aktif
A93: =IFERROR(__xludf.DUMMYFUNCTION("""COMPUTED_VALUE"""),"DBP02000091") -> DBP02000091 | B93: =IFERROR(__xludf.DUMMYFUNCTION("""COMPUTED_VALUE"""),"sakinahsalma.zhrh@gmail.com") -> sakinahsalma.zhrh@gmail.com | C93: 222222 | D93: Default | E93: Anggota | F93: Aktif
A94: =IFERROR(__xludf.DUMMYFUNCTION("""COMPUTED_VALUE"""),"DBP02000092") -> DBP02000092 | B94: =IFERROR(__xludf.DUMMYFUNCTION("""COMPUTED_VALUE"""),"astridamalya@gmail.com") -> astridamalya@gmail.com | C94: 222222 | D94: Default | E94: Anggota | F94: Aktif
A95: =IFERROR(__xludf.DUMMYFUNCTION("""COMPUTED_VALUE"""),"DBP02000093") -> DBP02000093 | B95: =IFERROR(__xludf.DUMMYFUNCTION("""COMPUTED_VALUE"""),"adhazuanm@gmail.com") -> adhazuanm@gmail.com | C95: 222222 | D95: Default | E95: Anggota | F95: Aktif
A96: =IFERROR(__xludf.DUMMYFUNCTION("""COMPUTED_VALUE"""),"DBP02000094") -> DBP02000094 | B96: =IFERROR(__xludf.DUMMYFUNCTION("""COMPUTED_VALUE"""),"vregita1@gmail.com") -> vregita1@gmail.com | C96: 222222 | D96: Default | E96: Anggota | F96: Aktif
A97: =IFERROR(__xludf.DUMMYFUNCTION("""COMPUTED_VALUE"""),"DBP02000095") -> DBP02000095 | B97: =IFERROR(__xludf.DUMMYFUNCTION("""COMPUTED_VALUE"""),"amalliaup@gmail.com") -> amalliaup@gmail.com | C97: 222222 | D97: Default | E97: Anggota | F97: Aktif
A98: =IFERROR(__xludf.DUMMYFUNCTION("""COMPUTED_VALUE"""),"DBP02000096") -> DBP02000096 | B98: =IFERROR(__xludf.DUMMYFUNCTION("""COMPUTED_VALUE"""),"muhammadfadli.muslimin@gmail.com") -> muhammadfadli.muslimin@gmail.com | C98: 222222 | D98: Default | E98: Anggota | F98: Aktif
A99: =IFERROR(__xludf.DUMMYFUNCTION("""COMPUTED_VALUE"""),"DBP02000097") -> DBP02000097 | B99: =IFERROR(__xludf.DUMMYFUNCTION("""COMPUTED_VALUE"""),"rizkiashuripratama45@gmail.com") -> rizkiashuripratama45@gmail.com | C99: 222222 | D99: Default | E99: Anggota | F99: Aktif
A100: =IFERROR(__xludf.DUMMYFUNCTION("""COMPUTED_VALUE"""),"DBP02000098") -> DBP02000098 | B100: =IFERROR(__xludf.DUMMYFUNCTION("""COMPUTED_VALUE"""),"naramia1693@gmail.com") -> naramia1693@gmail.com | C100: 222222 | D100: Default | E100: Anggota | F100: Aktif
...

Sheet Database
A1: ID Anggota | B1: Nama Lengkap | C1: Jenis Kelamin | D1: Tempat Lahir | E1: Tanggal Lahir | F1: Nomor Whatsapp | G1: Email | H1: Angkatan | I1: Pendidikan | J1: Universitas | K1: Fakultas | L1: Jurusan | M1: Negara Domisili | N1: Provinsi Domisili | O1: Kota Domisili | P1: Foto | Q1: LinkedIn | R1: Sektor Industri | S1: Jenis Pekerjaan | T1: Jabatan | U1: Nama Instansi | V1: Hobi | W1: Minat | X1: Komunitas Lain | Y1: Memiliki Usaha | Z1: Nama Usaha | AA1: Deskripsi Usaha | AB1: Bidang Usaha | AC1: Jabatan dalam Usaha | AD1: Lokasi Usaha | AE1: Persetujuan Data
A2: DBP00000000 | B2: HALO IKADBP | F2: 1234567890 | G2: halo.ikadbp@gmail.com | N2: , | P2: https://drive.google.com/file/d/1N9Bc4A9fu-dGoJXVf5LIR2gqW5eR1E_v/view?usp=drivesdk | Q2: aa | Y2: TIDAK
A3: DBP01000001 | B3: AKBAR HIDAYATULLAH | C3: LAKI-LAKI | E3: 31366 | G3: akbar.lawyer85@gmail.com | H3: 21 (2005/2006) | I3: S1 | J3: UNIVERSITAS TANJUNGPURA | K3: HUKUM | L3: ILMU HUKUM | M3: INDONESIA | N3: DKI JAKARTA, | O3: JAKARTA UTARA | P3: https://drive.google.com/open?id=1dZLLXnEqh1bvBprkkDfByp6VTdqn0zRG | Q3: https://www.linkedin.com/in/akbar-hidayatullah-926307a0?utm_source=share&utm_campaign=share_via&utm_content=profile&utm_medium=android_app | R3: HUKUM / LEGAL | S3: KURATOR | Y3: YA | AB3: HUKUM / JASA HUKUM
A4: DBP01000002 | B4: ANGGI VALENTINATA GOENADI | C4: LAKI-LAKI | E4: 32502 | G4: avgoenadi@gmail.com | P4: https://drive.google.com/open?id=18YkV4XqMuh3BHoCdIGzb0pWVeVE9wMGl
A5: DBP01000003 | B5: GEMA KUSUMAPUTRI | C5: PEREMPUAN | E5: 32891 | G5: gema.kusumaputri@gmail.com | P5: https://drive.google.com/open?id=1owUHoELFCvxo6tpP0WKM2G6U9ON9ywES
A6: DBP01000004 | B6: PUTU AGNIA | C6: PEREMPUAN | E6: 32697 | G6: putuagnia@gmail.com | P6: https://drive.google.com/open?id=1SyqgjYPKGOI33_ntdaxfSIL9YZUqqUUV
A7: DBP01000005 | B7: DANTE DARMAWANGSA | C7: LAKI-LAKI | E7: 30630 | G7: dante.darmawangsa@upi.edu
A8: DBP01000006 | B8: RATRI MUSTIKANING HANDOKO | C8: PEREMPUAN | E8: 31703 | G8: ratri.mustikaning.h@gmail.com | P8: https://drive.google.com/open?id=1UnoMc0RoeaTRuOzdL9TjzO-BMJgEHexF
A9: DBP01000007 | B9: PUTI KEMALA TANJUNG | C9: PEREMPUAN | E9: 32629 | G9: puti.kemala.tanjung@gmail.com
A10: DBP01000008 | B10: RORO AJENG SEKAR ARUM | C10: PEREMPUAN | E10: 33480 | G10: roroajengtaufik@gmail.com | P10: https://drive.google.com/open?id=1jyXayGvxEtA0vKip7ooJbDRBfZcSj9CE
A11: DBP01000009 | B11: WAWAY QODRATULLOH S | C11: LAKI-LAKI | E11: 30660 | G11: wayqodratulloh@gmail.com | P11: https://drive.google.com/open?id=1C2c3r1oBScuK8dK0AIsCP-Iyy1f5PGlO
A12: DBP01000010 | B12: GALIH PURWO HANDOKO | C12: LAKI-LAKI | E12: 31062 | G12: gp.handoko15@gmail.com | P12: https://drive.google.com/open?id=1AY4BtwQrHuDoyUH7iE1e3rQj_xCUj9hj
A13: DBP01000011 | B13: DODDY FIRMAN RAHMADI | C13: LAKI-LAKI | E13: 32202 | G13: doddyfirman@yahoo.com | P13: https://drive.google.com/open?id=12qS9yRfEvTGnMBciqxtMn5ztACQ0uWpU
A14: DBP01000012 | B14: HAWIT GURITNO | C14: LAKI-LAKI | E14: 32273 | G14: hawitguritno@gmail.com | P14: https://drive.google.com/open?id=1WLCrou2ykBlWIpVVKZ0chh9px9s6EYFC
A15: DBP01000013 | B15: MALA EKAYANTI | C15: PEREMPUAN | E15: 30976 | G15: malaekayanti@gmail.com | P15: https://drive.google.com/open?id=1_B8Szrryj4v2gosmG81cqsVjW95vEFyM
A16: DBP01000014 | B16: RIZKI ARIS YUNIANTO | C16: LAKI-LAKI | D16: MOJOKERTO | E16: 33042 | F16: 6285646452425 | G16: rizkiarisy@gmail.com | N16: , | P16: https://drive.google.com/file/d/1-s30EMjp_mlzrDWAzVug1IW32CamjLGZ/view?usp=drivesdk
A17: DBP01000015 | B17: FAZIA FEBRIANY | C17: PEREMPUAN | E17: 32551 | G17: fazia.febriany@gmail.com | P17: https://drive.google.com/open?id=1sWuKnUEnUtClk3zP06OYMsfSf34PV6Z9
A18: DBP01000016 | B18: JIILAN RANA WIJAYA | C18: LAKI-LAKI | E18: 34075 | G18: wijayajilan@gmail.com | P18: https://drive.google.com/open?id=16DNpFTZVMsuzW4mJdpZcXkNDRPEw81QV
A19: DBP01000017 | B19: NUR ROHMAN AZIS | C19: LAKI-LAKI | E19: 33665 | G19: nurrohmanazis1992@gmail.com | P19: https://drive.google.com/open?id=18s-qjy_Z49fkw7qPNTGcsw7ZyewHF5dK
A20: DBP01000018 | B20: DEDY HERIANSYAH | C20: LAKI-LAKI | P20: https://drive.google.com/open?id=1n5DJkjSBeOJIocVncNJoZDTqvsA4_yne
A21: DBP01000019 | B21: NICHO ADHI PUTRA TARIGAN | C21: LAKI-LAKI | E21: 33664 | G21: nicho.tarigan@gmail.com | P21: https://drive.google.com/open?id=1UIexVBPr4seYDJh4dzSeECNwuBe1HZ3X
A22: DBP01000020 | B22: OGY FABRIO MANDALA | C22: LAKI-LAKI | E22: 33750 | G22: Ogyfabrio@gmail.com | P22: https://drive.google.com/open?id=19gnLGoIgRchUheLlYobOkbJW0UQkwIwQ
A23: DBP01000021 | B23: SUHANDI | C23: LAKI-LAKI | E23: 32375 | G23: suhandies@gmail.com | P23: https://drive.google.com/open?id=1c2WL_PljoOhZTOeycmfKAuflpd8_zxEt
A24: DBP01000022 | B24: ATHA FITRAH RIYADHI | C24: LAKI-LAKI | E24: 35364 | G24: riyadhi.atha@gmail.com | P24: https://drive.google.com/open?id=1IJbfMnb1IfBKtdOUXm8T5gKJZZZa-icm
A25: DBP01000023 | B25: MARTHA NITA FLORENTINA S | C25: PEREMPUAN | E25: 32222 | G25: Marthanitaflorentinas@gmail.com | P25: https://drive.google.com/open?id=1BGvxMK--L8hYfZ8OnhWQQarfwA16HH0f
A26: DBP01000024 | B26: FERDINAND HIDAYAT | C26: LAKI-LAKI | E26: 32906 | G26: ferdinand.hiu@gmail.com | P26: https://drive.google.com/open?id=1c7YCvR6j6E1fH6c4RXKHpqk5AhGWylWi
A27: DBP01000025 | B27: SARITA GILLYAN KARTIKASARI | C27: PEREMPUAN | E27: 33575 | G27: sagitas@xlfutureleaders.com | P27: https://drive.google.com/open?id=16jdWbfRCCjJDI5heJhc9oPvwhU9xN7vM
A28: DBP01000026 | B28: RAHMANDHIKA FIRDAUZHA HARY HERNANDHA | C28: LAKI-LAKI | E28: 34402 | G28: herozh94@gmail.com | P28: https://drive.google.com/open?id=1Iudu6kfE3lR_VoRE8ZPam_kTrC3Sl5Tq
A29: DBP01000027 | B29: FAJAR HUDOYO | C29: LAKI-LAKI | E29: 36073 | G29: Fjrhdy11@gmail.com | P29: https://drive.google.com/open?id=1RHjjAMcOMflzpwaucX1ttgcug_HNb5_z
A30: DBP01000028 | B30: MOHAMMAD KHASAN | C30: LAKI-LAKI | E30: 31576 | G30: khasanm86@gmail.com | P30: https://drive.google.com/open?id=1X-tEB_zvK7eOZLrbf3gYwu1UjJutcJAV
A31: DBP01000029 | B31: ILHAM ARIFIN PAMBUDI | C31: LAKI-LAKI | E31: 35951 | G31: ilham.pbd@gmail.com | P31: https://drive.google.com/open?id=1J35rD2hwuXLvuUd9odBiSMmtSDRHJvHZ
A32: DBP01000030 | B32: FARIS SHAFI SULISTYA | C32: LAKI-LAKI | E32: 32826 | G32: shafi.faris33@gmail.com | P32: https://drive.google.com/open?id=17TbrGNPS4PsdMFI9EYyZhLsDaQ9MX3zX
A33: DBP01000031 | B33: HAPPY DYAH SIHANTI | C33: PEREMPUAN | E33: 32600 | F33: 08113660999 | G33: Hapinksihanti89@gmail.com | H33: 25 (2009/2010) | I33: S1 | J33: UNIVERSITAS MERDEKA MALANG | K33: PSIKOLOGI | L33: PSIKOLOGI | M33: INDONESIA | N33: JAWA TIMUR, | O33: MALANG | P33: https://drive.google.com/file/d/1-FDdPQCnFAYOhJX2KqC6cYcUOxZwvzRD/view?usp=drivesdk | Q33: Happy dyah sihanti | R33: KEUANGAN / PERBANKAN / ASURANSI | S33: MARKETING / SALES / PR | T33: PREMIER BANKING MANAGER | U33: PT BANK OCBC | V33: MENYANYI | Y33: TIDAK
A34: DBP01000032 | B34: JANISATYA DIDO | C34: LAKI-LAKI | G34: didopranata@gmail.com
A35: DBP01000033 | B35: PUTU NUNIEK HUTNALEONTINA | C35: PEREMPUAN | E35: 32597 | G35: putununiek89@unhi.ac.id | P35: https://drive.google.com/open?id=19_oyIC75DRXnB5wCXBEXldXyeWoYJjy0
A36: DBP01000034 | B36: NESER IKE CAHYANINGRUM | C36: PEREMPUAN | E36: 32762 | G36: neserike@gmail.com | P36: https://drive.google.com/open?id=1QaAUYJapy1sVfPL-A55D8blTBnLkZo8P
A37: DBP01000035 | B37: YUDITH SANDRI RONDONUWU | C37: PEREMPUAN | E37: 31247 | G37: yudith.tm@gmail.com | P37: https://drive.google.com/open?id=1h8L2hMJfsjrLbya2H3a1Rb0QFZ22YI1u
A38: DBP01000036 | B38: ZULQADRI SUAIB | C38: LAKI-LAKI
A39: DBP01000037 | B39: DEIDRA NATALIE TOMASOA | C39: PEREMPUAN | E39: 35058 | G39: deidranataliet@gmail.com | P39: https://drive.google.com/open?id=1jpOPghzMWRoumgKehyNWYB-ubikpvZCr
A40: DBP01000038 | B40: GALIO RUDOLFO DIAN BURDAMES | C40: LAKI-LAKI | E40: 33548 | G40: dianboer@gmail.com | P40: https://drive.google.com/open?id=190zi2YIW7GxUB5zmCopJnMZRkPWHEzNv
A41: DBP01000039 | B41: SANTI PELITAWATI | C41: PEREMPUAN | E41: 31138 | G41: pelitawati1@gmail.com | P41: https://drive.google.com/open?id=1so__bqo6cVN9YuHKagCbntvQGMAJC70X
A42: DBP01000040 | B42: RICO HALIM | C42: LAKI-LAKI | D42: BANDA ACEH | E42: 36646 | F42: 6282360853214 | G42: ricohalim46@gmail.com | H42: 36 (2020/2021) | I42: S2 | J42: UNIVERSITAS SYIAH KUALA | K42: MATEMATIKA DAN ILMU PENGETAHUAN ALAM | L42: INFORMATIKA | M42: INDONESIA | N42: BANTEN, | O42: KOTA TANGERANG | P42: https://drive.google.com/file/d/1DbgpRZP_0uL4_YqzSZ8HBr-oUlu9r_6D/view?usp=drivesdk | Q42: https://www.linkedin.com/in/ricohalim/ | R42: PENDIDIKAN / AKADEMISI | S42: EDUKASI (DOSEN / GURU / PENELITI) | T42: DOSEN | U42: UNIVERSITAS BINA NUSANTARA | V42: MEMBACA, VIBE CODING | W42: CODING | X42: TIDAK ADA | Y42: TIDAK
A43: DBP01000041 | B43: CITRA ASMARA | C43: PEREMPUAN | E43: 30398 | G43: citra.asmara.83@gmail.com
A44: DBP01000042 | B44: CYNTHIA KIRANA PUTERI | C44: PEREMPUAN | E44: 33294 | G44: cynthiakp.ckp@gmail.com | P44: https://drive.google.com/open?id=1ITPzsfnnTJdlr0sxbCyBEXSXh6ec9aTT
A45: DBP01000043 | B45: S. RIFAI | C45: LAKI-LAKI | E45: 32311 | G45: solehrifai@gmail.com | P45: https://drive.google.com/open?id=11VPG7DiWYxLbmvXJtsyE8SS2HvJXyF9T
A46: DBP01000044 | B46: IQBAL F ANSHARI | C46: LAKI-LAKI | E46: 32553 | F46: 081324985723 | G46: iqbalfa5@gmail.com | H46: 25 (2009/2010) | I46: S1 | J46: UNIVERSITAS PENDIDIKAN INDONESIA | K46: TEKNIK | L46: TEKNIK ELEKTRO | M46: INDONESIA | N46: JAWA BARAT, | O46: BANDUNG | P46: https://drive.google.com/file/d/1Nm4bQzuiOPDNeO15r_PjOYYYU2rHMJBX/view?usp=drivesdk | Q46: Iqbal Fakhruzzaman Anshari | R46: PERIKANAN | S46: WIRASWASTA | T46: OWNER | U46: CV GOLDEN VANN | V46: GAME | W46: BISNIS | X46: BISNIS | Y46: YA | AB46: PERDAGANGAN DAN DISTRIBUSI
A47: DBP01000045 | B47: ANNISA LATUMAHINA | C47: PEREMPUAN | E47: 34862 | G47: nisalatu1995@gmail.com | P47: https://drive.google.com/open?id=162HEcaM0mOkJC1R9vC1g_1bnabLzDN3v
A48: DBP01000046 | B48: DIKKY NUR FAIZAL | C48: LAKI-LAKI | E48: 36927 | G48: faizaldikky@gmail.com | P48: https://drive.google.com/open?id=1p8kTKdDB88UJGUeb6t7U-mk2KDlalVaP
A49: DBP01000047 | B49: VERONICA MONTEIRO DOSANTOS NENO | C49: PEREMPUAN | E49: 37131 | F49: 089506401643 | G49: veronicamdn9@gmail.com | H49: 37 (2021/2022) | I49: S1 | J49: UNIVERSITAS SEMARANG | K49: EKONOMI | L49: AKUNTANSI | M49: INDONESIA | N49: JAWA TENGAH, | O49: DEMAK | P49: https://drive.google.com/open?id=1wK3GUbC1oFMFiePIYUvrP71_tOhysYYN | R49: KONSTRUKSI / PROPERTI | S49: MARKETING / SALES / PR | T49: STAFF | U49: SUTINDO RAYA MULIA | V49: BERENANG | Y49: TIDAK
A50: DBP01000048 | B50: RIKA RAHMAYUNI | C50: PEREMPUAN | F50: 082284348404 | G50: rikarahmayuni08@gmail.com | H50: 33 (2017/2018) | I50: S2 | J50: UNIVERSITAS ANDALAS | K50: EKONOMI | L50: MANAJEMEN | M50: INDONESIA | N50: DKI JAKARTA, | O50: JAKARTA PUSAT | P50: https://drive.google.com/file/d/1JkzY29Ay90JgdxlfxMWkfw4HVms3NktN/view?usp=drivesdk | Q50: Rika Rahmayuni | R50: MEDIA / KREATIF / HIBURAN | S50: EVENT ORGANIZER | V50: TRAVELLING, MEMBACA | Y50: TIDAK
A51: DBP01000049 | B51: ASTRA BETA LIECHARLIE
A52: DBP01000050 | B52: PANDU SUKMA KISI SHESA | C52: LAKI-LAKI | E52: 36133 | G52: pandusukmaks@gmail.com | P52: https://drive.google.com/open?id=173SSe0h-A0sJvma11uJqcYFO9GurwlKk
A53: DBP01000051 | B53: YUKA PUTRI RENOSURI MANTI | C53: PEREMPUAN | E53: 36401 | G53: yukaprm29@gmail.com | P53: https://drive.google.com/open?id=1S_1UpxDwPUmyN25tP0iEMn3ObYaqi5be
A54: DBP01000052 | B54: DUDIH SUTRISMAN | C54: LAKI-LAKI | E54: 33992 | G54: dudih.sutrisman@yahoo.co.id | P54: https://drive.google.com/open?id=1yANSGMdPO91WKPf4UIi-SLtnNeeR6fxK
A55: DBP01000053 | B55: EKO BAGUS CAHYO PURNOMO | C55: LAKI-LAKI | E55: 32007 | G55: baguz87@gmail.com | P55: https://drive.google.com/open?id=1u2ig8Xma6-kcHxh-KMNR1DmRvWUC2hYz
A56: DBP01000054 | B56: ANDRE SEPTIAN NOLZA | C56: LAKI-LAKI | E56: 36776 | G56: andreseptian227@gmail.com | P56: https://drive.google.com/open?id=1HQ2UkfLrhSpXjcUr0FXpInmtamkOYJEr
A57: DBP01000055 | B57: USWATUN CHASANAH | C57: PEREMPUAN | E57: 32823 | G57: uswachassanah@gmail.com
A58: DBP01000056 | B58: BAYU RAHMAT AKBAR | C58: LAKI-LAKI | E58: 44853 | G58: akbar.bayurahmat@gmail.com | P58: https://drive.google.com/open?id=1SGHdaRIhlykDnJ24bmaAz9W8vdFj8WrR
A59: DBP01000057 | B59: FITRA ARRAHMA | C59: PEREMPUAN | E59: 36750 | G59: Fitraarrahma12@gmail.com | P59: https://drive.google.com/open?id=1rOlt7QGwcTH88eGsvwMtKQ8pM_oUSkGy
A60: DBP01000058 | B60: NIDYA HENDRAWAN | C60: PEREMPUAN | E60: 36487 | G60: nidya.hendrawan.tjong@gmail.com | P60: https://drive.google.com/open?id=1Kpk2D388wW8_sG5MYahU2QaUWoP036Wm
A61: DBP01000059 | B61: AMELIA AUGUSTIN YOLANDA | C61: PEREMPUAN | E61: 36768 | G61: ameliaaugustin00@gmail.com | P61: https://drive.google.com/open?id=1xitA0iIypFevs35I7yr1Zg_JE7kGhvPW
A62: DBP01000060 | B62: FARID NOOR ROMADLON | C62: LAKI-LAKI | E62: 45475 | G62: farid.noor@umk.ac.id | P62: https://drive.google.com/open?id=1YLsRqt8bcUmny_FZOatF-sIWAAksNcG6
A63: DBP01000061 | B63: SATRIO HERLAMBANG ADI PANGESTU | C63: LAKI-LAKI | E63: 35035 | G63: shapangestu@gmail.com | P63: https://drive.google.com/open?id=1hJAMFSdRnjJAZhGCdQCpqptZ-Xc2dKb3
A64: DBP01000062 | B64: IKA REZVANI APRITA | C64: PEREMPUAN | E64: 32240 | G64: ikarezvaniaprita@gmail.com | P64: https://drive.google.com/open?id=1x-ySyy5MY80nW6z0tNanNOB5BGuz1UmQ
A65: DBP01000063 | B65: M TAUFIK HIDAYAT | C65: LAKI-LAKI | D65: MEDAN | E65: 36416 | G65: Ikrimahtaufikhidayat@gmail.com | H65: 35 (2018/2019) | P65: https://drive.google.com/open?id=1TgfA5juiLBZHsSr2g-Bc-cb4yYxSPHLd
A66: DBP01000064 | B66: RISYA SASRI | C66: PEREMPUAN | E66: 32942 | G66: Sasrisyapin@gmail.com | P66: https://drive.google.com/open?id=1fA-YfU58crqklSL36dHUN4IHSDNtewk7
A67: DBP01000065 | B67: ACHMAD RIZAL FIRMANSYAH | C67: LAKI-LAKI | E67: 36633 | F67: 087825505313 | G67: firmansyahrizal21@gmail.com | H67: 36 (2020/2021) | I67: S1 | J67: UNIVERSITAS NEGERI SEMARANG | K67: TEKNIK | L67: TEKNIK MESIN | M67: INDONESIA | N67: JAWA TIMUR, | O67: TUBAN | P67: https://drive.google.com/open?id=1KaOaw-YSnlXdjMABydTKFlqL7PW0Q7Jh | Q67: Achmad Rizal Firmansyah | R67: MANUFAKTUR / PABRIK | S67: ENGINEERING / TEKNIK (SIPIL, MESIN, ELEKTRO, DLL) | T67: SUPERITENDANT | U67: PT. SOLUSI BANGUN INDONESIA | V67: GAME, OLAHRAGA, FILM | W67: BISNIS DAN USAHA | X67: TIDAK ADA | Y67: TIDAK
A68: DBP01000066 | B68: HENDI HIDAYAT | C68: LAKI-LAKI | E68: 30389 | G68: hendi140383@gmail.com
A69: DBP01000067 | B69: VIXKY TANUDJAJA | C69: PEREMPUAN | E69: 33875 | G69: vixkytanudjaja@gmail.com | P69: https://drive.google.com/open?id=1tkmappvtBWkJhmE9Q48g5oPB5X6ekZ4l
A70: DBP01000068 | B70: ARIEF DUROCHMAN | C70: LAKI-LAKI | E70: 31085 | G70: annabelle230413@gmail.com | P70: https://drive.google.com/open?id=1ouhanVc0W9q-YXUwFYv_Ay3wJojS5yiT
A71: DBP01000069 | B71: DENI DWI RUSMAWAN | C71: LAKI-LAKI | E71: 33175 | G71: denirusmawan826@gmail.com | P71: https://drive.google.com/open?id=1YIbNHOhkhQ1EC1TyZ9VE5KErzSCFDwDx
A72: DBP01000070 | B72: SALSA A. KIRANA | P72: https://drive.google.com/open?id=10-SEAhS8zebjgrsv6u8sX3IIG_d_btiq
A73: DBP01000071 | B73: EVA ANGELINE | C73: PEREMPUAN | E73: 36983 | G73: Elisabethevangeline31@gmail.com | P73: https://drive.google.com/open?id=10cY0VS7lNn9u-1kVdMyjZRt0oTxeRVZ7
A74: DBP01000072 | B74: INTAN LUTVIANA WULANDARI | C74: PEREMPUAN | E74: 37133 | G74: intanlutviana39@gmail.com | P74: https://drive.google.com/open?id=1x_iDrk7eSedI0ksf4XqJzviCs0NbL-5A
A75: DBP01000073 | B75: ANNISA TRIANA TALMERA | C75: PEREMPUAN | E75: 36769 | G75: annisatalmera@gmail.com | P75: https://drive.google.com/open?id=1IPsJ48_0s2pZHm1FmzD93ghevJPiZsrH
A76: DBP01000074 | B76: GABY PANG LYLIEN | C76: PEREMPUAN | E76: 36248 | G76: gabypanglylien@gmail.com | P76: https://drive.google.com/open?id=1ess-d8GopMkvsZXwHP5vtd_WrTSWJhxw
A77: DBP01000075 | B77: GREGORIUS GOKLAS SILABAN | C77: LAKI-LAKI | E77: 35910 | G77: Putrasilaban691@gmail.com | P77: https://drive.google.com/open?id=1VfdBEC1LakgloNunnB85uXI24oIpgt4K
A78: DBP01000076 | B78: SUPARMAN WAKIDI | C78: LAKI-LAKI | E78: 36082 | F78: 085399310430 | G78: suparmanwakidi.s.ak@gmail.com | H78: 34 (2018/2019) | I78: S1 | J78: UNIVERSITAS TADULAKO | K78: EKONOMI DAN BISNIS | L78: AKUNTANSI | M78: INDONESIA | N78: DKI JAKARTA, | O78: JAKARTA BARAT | P78: https://drive.google.com/open?id=1yB4vIj9U7441LTBiv_qJ2OS_j79wX_CI | Q78: Suparman Wakidi | R78: RETAIL | S78: SALES DEVELOPMENT EXECUTIVE | T78: SUPERVISOR | U78: PT. SUPRA BOGA LESTARI TBK | V78: BADMINTON | Y78: TIDAK
A79: DBP01000077 | B79: RUDY DWI PRASETYO | C79: LAKI-LAKI | E79: 34802 | G79: dwipras88@gmail.com | P79: https://drive.google.com/open?id=1nAYgExEZSOZxZr2waObXHZ8njpQC2Zry
A80: DBP01000078 | B80: DENILSON | C80: LAKI-LAKI | E80: 36641 | F80: 089676176088 | G80: budidennn@gmail.com | H80: 36 (2020/2021) | I80: S1 | J80: UNIVERSITAS TANJUNGPURA | K80: EKONOMI DAN BISNIS | L80: EKONOMI PEMBANGUNAN | M80: INDONESIA | N80: KALIMANTAN BARAT, | O80: PONTIANAK | P80: https://drive.google.com/open?id=1-vncNTgnQBU3eU48FCENxGZubP82l_gF | R80: PERTANIAN / PERKEBUNAN | S80: LOGISTIK / SUPPLY CHAIN / OPERASIONAL | T80: FFB PURCHASE | U80: PT PALMA LESTARI PUTRA BORNEO | Y80: TIDAK
A81: DBP01000079 | B81: MUHAMMAD RIFQI RIZQULLAH | C81: LAKI-LAKI | E81: 36913 | G81: rizqullahrifqi22@gmail.com | P81: https://drive.google.com/open?id=1iT0NfaLZJ3ywQt0gviWIJ4t-gfha00zj
A82: DBP02000080 | B82: MUHAMMAD ADIB ARDIANTO | C82: LAKI-LAKI | D82: KUDUS | E82: 37050 | F82: 6285601029298 | G82: adibardianto21@gmail.com | H82: 38 (2022/2023) | I82: S1 | J82: UNIVERSITAS MURIA KUDUS | P82: https://drive.google.com/open?id=1ssB311OS-PYbfuQbdFIrTBT50WHfWOkE
A83: DBP02000081 | B83: EDWIN BUDI SETIAWAN | C83: LAKI-LAKI | D83: TEGAL | E83: 35334 | F83: 6281911654518 | G83: edwin.setiawan26@gmail.com | H83: 32 (2016/2017) | I83: S1 | J83: UNIVERSITAS NEGERI SEBELAS MARET | N83: Jawa Barat | O83: Kota Bogor | P83: https://drive.google.com/open?id=1i4PIby1GV6vyWPTaAABerxcqmqdi9SgZ | Q83: https://www.linkedin.com/in/edwin-budi-setiawan?utm_source=share&utm_campaign=share_via&utm_content=profile&utm_medium=ios_app | S83: Pegawai Swasta | T83: R&D Associate | U83: PT. Nutrifood | V83: Mendengarkan musik, Menonton film dan acara televisi, Berolahraga (seperti lari, bersepeda, yoga, dan lainnya) | W83: Kebugaran dan kesehatan, Petualangan dan eksplorasi alam, Teknologi dan inovasi, Musik (mendengarkan, memainkan instrumen, produksi musik), Pembelajaran bahasa asing | X83: - | Y83: Tidak | AE83: Ya
A84: DBP02000082 | B84: WINDAHAYATI | C84: PEREMPUAN | D84: BOGOR | E84: 33252 | F84: 6285694048865 | G84: ndawindahayati@gmail.com | H84: 27 (2011/2012) | I84: S1 | J84: UNIVERSITAS ANDALAS | K84: Matematika dan Ilmu Pengetahun Alam | L84: Biologi
A85: DBP02000083 | B85: IKA DWIYULITA | C85: PEREMPUAN | D85: UJUNG PANDANG | E85: 35613 | F85: 6285342117847 | G85: ikadwiyulita@gmail.com | H85: 32 (2016/2017) | I85: S1 | J85: LAINNYA
A86: DBP02000084 | B86: EKO SUHADINATA | C86: LAKI-LAKI | D86: PAGAR ALAM | E86: 35810 | F86: 6282281478969 | G86: ekosuhadinata4312@gmail.com | H86: 33 (2017/2018) | I86: S1 | J86: UNIVERSITAS ISLAM NEGERI SUNAN KALIJAGA
A87: DBP02000085 | B87: ARIS PUTRA WIBOWO | C87: LAKI-LAKI | D87: PACITAN | E87: 35860 | F87: 6281326854935 | G87: wibowoaris297@gmail.com | H87: 35 (2019/2020) | I87: S1 | J87: UNIVERSITAS DIPONEGORO
A88: DBP02000086 | B88: R. MUHAMMAD SYAEPUL MUZIEB MULYANA | C88: LAKI-LAKI | D88: CIANJUR | E88: 37103 | F88: 6285723234643 | G88: muziebmulyana@gmail.com | H88: 38 (2022/2023) | I88: S1 | J88: UNIVERSITAS JENDERAL ACHMAD YANI | K88: Ilmu Sosial dan Ilmu Politik | L88: Hubungan Internasional
A89: DBP02000087 | B89: MANULLANG, SABAM | C89: LAKI-LAKI | D89: SAMARINDA | E89: 37042 | F89: 6282255897662 | G89: sabamm31@gmail.com | H89: 37 (2021/2022) | I89: S1 | J89: UNIVERSITAS DIPONEGORO | K89: Teknik | L89: Teknik Industri
A90: DBP02000088 | B90: DELIANA | C90: PEREMPUAN | D90: PONTIANAK | E90: 33366 | F90: 6281352080513 | G90: delidelmonte@gmail.com | H90: 27 (2011/2012) | I90: S1 | J90: UNIVERSITAS TANJUNGPURA
A91: DBP02000089 | B91: ALIFYAA RAHMANITA | C91: PEREMPUAN | D91: JAKARTA | E91: 37318 | F91: 6281286830303 | G91: alifyaarahmanita@gmail.com | H91: 37 (2021/2022) | I91: S1 | J91: LAINNYA | K91: Ekonomi | L91: Manajemen
A92: DBP02000090 | B92: HANAA FAKHRANI | C92: PEREMPUAN | D92: JAKARTA | E92: 37647 | F92: 6281283232601 | G92: hanafakhrani.hf@gmail.com | H92: 39 (2023/2024) | I92: S1 | J92: INSTITUT KESENIAN JAKARTA | K92: Seni Rupa dan Desain | L92: Desain Interior
A93: DBP02000091 | B93: SAKINAH SALMA ZAHIRAH | C93: PEREMPUAN | D93: BANDUNG | E93: 35346 | F93: 6383100154040 | G93: sakinahsalma.zhrh@gmail.com | H93: 33 (2017/2018) | I93: S1 | J93: UNIVERSITAS PENDIDIKAN INDONESIA
A94: DBP02000092 | B94: BAIQ ASTRID AMALYA NUANSHARI | C94: PEREMPUAN | D94: LOMBOK | E94: 37013 | F94: 6281779689036 | G94: astridamalya@gmail.com | H94: 37 (2021/2022) | I94: S1 | J94: UNIVERSITAS TRUNOJOYO | K94: Pertanian | L94: Ilmu Kelautan
A95: DBP02000093 | B95: ADHA ZUAN MUZAQI HAMID | C95: LAKI-LAKI | D95: KEDIRI | E95: 36601 | F95: 6281330744313 | G95: adhazuanm@gmail.com | H95: 35 (2019/2020) | I95: D4 | J95: POLITEKNIK NEGERI MALANG | K95: Teknik | L95: Teknik Elektro
A96: DBP02000094 | B96: VIONA REGITA CAHAYA ISKANDAR | C96: PEREMPUAN | D96: BANJARMASIN | E96: 37362 | F96: 6287877687979 | G96: vregita1@gmail.com | H96: 37 (2021/2022) | I96: S1 | J96: UNIVERSITAS LAMBUNG MANGKURAT | K96: Ekonomi | L96: Ilmu Ekonomi dan Studi Pembangunan
A97: DBP02000095 | B97: AMALLIA UTAMI PUTRI | C97: PEREMPUAN | D97: TELUK BETUNG | E97: 33757 | F97: 6287778512612 | G97: amalliaup@gmail.com | H97: 28 (2012/2013) | I97: S1 | J97: UNIVERSITAS SULTAN AGENG TIRTAYASA | K97: Ilmu Sosial dan Ilmu Politik | L97: Ilmu Komunikasi
A98: DBP02000096 | B98: MUHAMMAD FADLI MUSLIMIN | C98: LAKI-LAKI | D98: UJUNG PANDANG | E98: 33452 | F98: 6282291513675 | G98: muhammadfadli.muslimin@gmail.com | H98: 28 (2012/2013) | I98: S1 | J98: UNIVERSITAS MUSLIM INDONESIA | K98: Sastra Inggris | L98: Sastra Inggris
A99: DBP02000097 | B99: RIZKI ASHURI PRATAMA | C99: LAKI-LAKI | D99: KARANGANYAR | E99: 37024 | F99: 628996668479 | G99: rizkiashuripratama45@gmail.com | H99: 37 (2021/2022) | I99: S1 | J99: UNIVERSITAS TRUNOJOYO
A100: DBP02000098 | B100: NARAMIA WIJAYA | C100: PEREMPUAN | D100: JAKARTA | E100: 37880 | F100: 6289506332173 | G100: naramia1693@gmail.com | H100: 39 (2023/2024) | I100: S1 | J100: UNIVERSITAS TARUMANAGARA | K100: Teknologi Informasi | L100: Teknik Informatika
...

Sheet TempPendaftar
A1: Timestamp | B1: Status | C1: Nama Lengkap | D1: Jenis Kelamin | E1: Tempat Lahir | F1: Tanggal Lahir | G1: Nomor Whatsapp | H1: Email | I1: PIN | J1: Angkatan | K1: Pendidikan | L1: Universitas | M1: Fakultas | N1: Jurusan | O1: Negara Domisili | P1: Provinsi Domisili | Q1: Kota Domisili | R1: Foto | S1: LinkedIn | T1: Sektor Industri | U1: Jenis Pekerjaan | V1: Jabatan | W1: Nama Instansi | X1: Hobi | Y1: Minat | Z1: Komunitas Lain | AA1: Memiliki Usaha | AB1: Nama Usaha | AC1: Deskripsi Usaha | AD1: Bidang Usaha | AE1: Jabatan dalam Usaha | AF1: Lokasi Usaha | AG1: Persetujuan Data
A2: 45990.87 | B2: Pending | C2: IKATAN ALUMNI DJARUM BEASISWA PLUS | D2: - | E2: JAKARTA | F2: 2025-11-29 | G2: 08123456789 | H2: halo.ikadbp@gmail.co.id | I2: 123456 | J2: 30 (2014/2015) | K2: S1 | L2: UNIVERSITAS BINA NUSANTARA | M2: TEKNIK | N2: TEKNIK INFORMATIKA | O2: INDONESIA | P2: DKI JAKARTA | Q2: TANGERANG | R2: https://drive.google.com/file/d/1bbEjPePIqr7Wjazm0exVx3lZ5FgSzD70/view?usp=drivesdk | T2: LAINNYA | U2: EDUKASI (DOSEN / GURU / PENELITI) | V2: DOSEN | W2: UNIVERSITAS BINA NUSANTARA | AA2: Ya | AD2: PERTANIAN DAN PETERNAKAN | AG2: on

Sheet Agenda
A1: ID Agenda | B1: Judul Kegiatan | C1: Tanggal | D1: Deskripsi Singkat | E1: Lokasi | F1: Status
A2: KT001 | B2: Pemilu Ketua Umum | C2: 45912 | D2: Pemilihan Ketua Umum | E2: Zoom | F2: Tutup

Sheet DataPartisipan
A1: Timestamp | B1: ID Agenda | C1: Judul Kegiatan | D1: ID Anggota | E1: Anggota | F1: Email | G1: No WA
A2: 45999.794 | B2: KT001 | C2: Pemilu Ketua Umum | D2: DBP01000040 | E2: RICO HALIM | F2: ricohalim46@gmail.com | G2: 6282360853214

Sheet Login Log
A1: Timestamp | B1: Email | C1: ID Anggota | D1: Status | E1: Deskripsi
A2: 45990.728 | B2: ricohalim46@gmail.com | C2: DBP01000040 | D2: Sukses | E2: Login OK
A3: 45990.73 | B3: rizkiarisy@gmail.com | C3: DBP01000014 | D3: Gagal | E3: Wrong PIN
A4: 45990.73 | B4: rizkiarisy@gmail.com | C4: DBP01000014 | D4: Sukses | E4: Login OK
A5: 45990.731 | B5: ricohalim46@gmail.com | C5: DBP01000040 | D5: Sukses | E5: Login OK
A6: 45990.739 | B6: ricohalim46@gmail.com | C6: DBP01000040 | D6: Sukses | E6: Login OK
A7: 45990.739 | B7: dudih.sutrisman@yahoo.co.id | C7: DBP01000052 | D7: Gagal | E7: Wrong PIN
A8: 45990.74 | B8: dudih.sutrisman@yahoo.co.id | C8: DBP01000052 | D8: Sukses | E8: Login OK
A9: 45990.741 | B9: ricohalim46@gmail.com | C9: DBP01000040 | D9: Sukses | E9: Login OK
A10: 45990.741 | B10: faizaldikky@gmail.com | C10: DBP01000046 | D10: Sukses | E10: Login OK
A11: 45990.752 | B11: faizaldikky@gmail.com | C11: DBP01000046 | D11: Sukses | E11: Login OK
A12: 45990.753 | B12: ricohalim46@gmail.com | C12: DBP01000040 | D12: Sukses | E12: Login OK
A13: 45990.757 | B13: faizaldikky@gmail.com | C13: DBP01000046 | D13: Sukses | E13: Login OK
... A84: 46008.768 | B84: budidennn@gmail.com | C84: DBP01000078 | D84: Sukses | E84: Login OK
A85: 46008.768 | B85: ilham.pbd@gmail.com | D85: Gagal | E85: Email not found
A86: 46008.768 | B86: hapinksihanti89@gmail.com | C86: DBP01000031 | D86: Gagal | E86: Wrong PIN
A87: 46008.768 | B87: ilham.pbd@gmail.com | C87: DBP01000029 | D87: Sukses | E87: Login OK
A88: 46008.768 | B88: rikarahmayuni08@gmail.com | C88: DBP01000048 | D88: Sukses | E88: Login OK
A89: 46008.77 | B89: akbar.lawyer85@gmail.com | C89: DBP01000001 | D89: Sukses | E89: Login OK
A90: 46008.77 | B90: rikarahmayuni08@gmail.com | C90: DBP01000048 | D90: Sukses | E90: Login OK
A91: 46008.771 | B91: neserike@gmail.com | C91: DBP01000034 | D91: Sukses | E91: Login OK
A92: 46008.771 | B92: akbar.lawyer85@gmail.com | C92: DBP01000001 | D92: Sukses | E92: Login OK
A93: 46008.772 | B93: suparmanwakidi.s.ak@gmail.com | C93: DBP01000076 | D93: Sukses | E93: Login OK
A94: 46008.772 | B94: hapinksihanti89@gmail.com | C94: DBP01000031 | D94: Sukses | E94: Login OK
A95: 46008.776 | B95: ikarezvaniaprita@gmail.com | C95: DBP01000062 | D95: Sukses | E95: Login OK

Sheet Ref
A1: Jenis Kelamin | B1: Angkatan | C1: Pendidikan | D1: Negara | E1: Provinsi | F1: Universitas | G1: Fakultas | H1: Jenis Pekerjaan | I1: Bidang Usaha | J1: Memiliki Usaha | K1: Sektor Industri
A2: LAKI-LAKI | B2: 18 (2002/2003) | C2: D4 | D2: INDONESIA | E2: ACEH | F2: IAIN KUDUS | G2: HUKUM | H2: AKUNTANSI / KEUANGAN / PAJAK | I2: MAKANAN DAN MINUMAN | J2: Ya | K2: PEMERINTAHAN / BUMN
A3: PEREMPUAN | B3: 19 (2003/2004) | C3: S1 | D3: AFGANISTAN | E3: BALI | F3: INSTITUT KESENIAN JAKARTA | G3: ILMU SOSIAL DAN ILMU POLITIK | H3: ADMINISTRASI / SEKRETARIS | I3: KREATIF DAN SENI | J3: Tidak | K3: PENDIDIKAN / AKADEMISI
B4: 20 (2004/2005) | C4: S2 | D4: AFRIKA SELATAN | E4: BANTEN | F4: INSTITUT PERTANIAN BOGOR | H4: ARSITEK / DESAIN INTERIOR | I4: PENDIDIKAN DAN PELATIHAN | K4: KESEHATAN / MEDIS
B5: 21 (2005/2006) | D5: ALBANIA | E5: BENGKULU | F5: INSTITUT SENI INDONESIA YOGYAKARTA | H5: DESAIN GRAFIS / MULTIMEDIA / KREATIF | I5: MODE DAN PAKAIAN | K5: TEKNOLOGI / IT / STARTUP
B6: 22 (2006/2007) | D6: ALJAZAIR | E6: DI YOGYAKARTA | F6: INSTITUT TEKNOLOGI BANDUNG | H6: DOKTER / PERAWAT / TENAGA MEDIS | I6: PERDAGANGAN DAN DISTRIBUSI | K6: KEUANGAN / PERBANKAN / ASURANSI
B7: 23 (2007/2008) | D7: AMERIKA SERIKAT | E7: DKI JAKARTA | F7: INSTITUT TEKNOLOGI HARAPAN BANGSA | H7: EDUKASI (DOSEN / GURU / PENELITI) | I7: TEKNOLOGI DAN DIGITAL | K7: KONSTRUKSI / PROPERTI
B8: 24 (2008/2009) | D8: ANDORRA | E8: GORONTALO | F8: INSTITUT TEKNOLOGI KALIMANTAN | H8: ENGINEERING / TEKNIK (SIPIL, MESIN, ELEKTRO, DLL) | I8: KONSTRUKSI DAN PROPERTI | K8: ENERGI / MIGAS / PERTAMBANGAN
B9: 25 (2009/2010) | D9: ANGOLA | E9: JAMBI | F9: INSTITUT TEKNOLOGI NASIONAL | H9: HUKUM / LEGAL / NOTARIS | I9: PENYEDIAAN BARANG DAN PELAYANAN | K9: MANUFAKTUR / PABRIK
B10: 26 (2010/2011) | D10: ANTIGUA DAN BARBUDA | E10: JAWA BARAT | F10: INSTITUT TEKNOLOGI SEPULUH NOPEMBER | H10: HRD / PERSONALIA / REKRUTMEN | I10: MANUFAKTUR DAN PRODUKSI | K10: RETAIL / PERDAGANGAN / FMCG
B11: 27 (2011/2012) | D11: ARAB SAUDI | E11: JAWA TENGAH | F11: POLITEKNIK ELEKTRONIKA NEGERI SURABAYA | H11: IT / SOFTWARE / DATA | I11: PERTANIAN DAN PETERNAKAN | K11: MEDIA / KREATIF / HIBURAN
B12: 28 (2012/2013) | D12: ARGENTINA | E12: JAWA TIMUR | F12: POLITEKNIK NEGERI BANDUNG | H12: JURNALIS / PENULIS / CONTENT | I12: KOMUNIKASI DAN MEDIA | K12: HUKUM / LEGAL
B13: 29 (2013/2014) | D13: ARMENIA | E13: KALIMANTAN BARAT | F13: POLITEKNIK NEGERI BATAM | H13: KONSULTAN / ANALIS | I13: KESEHATAN DAN KECANTIKAN | K13: PARIWISATA / HOTEL / F&B
B14: 30 (2014/2015) | D14: AUSTRALIA | E14: KALIMANTAN SELATAN | F14: POLITEKNIK NEGERI MALANG | H14: LOGISTIK / SUPPLY CHAIN / OPERASIONAL | I14: HIBURAN DAN REKREASI | K14: LOGISTIK / TRANSPORTASI
B15: 31 (2015/2016) | D15: AUSTRIA | E15: KALIMANTAN TENGAH | F15: POLITEKNIK NEGERI SAMARINDA | H15: MARKETING / SALES / PR | I15: TRANSPORTASI DAN LOGISTIK | K15: PERTANIAN / PERKEBUNAN
B16: 32 (2016/2017) | D16: AZERBAIJAN | E16: KALIMANTAN TIMUR | F16: POLITEKNIK NEGERI SEMARANG | H16: PELAYANAN PUBLIK / ASN / TNI / POLRI | I16: KEUANGAN DAN INVESTASI | K16: LSM / NON-PROFIT
... B18: 34 (2018/2019) | D18: BAHRAIN | E18: KEPULAUAN BANGKA BELITUNG | F18: SEKOLAH TINGGI ILMU EKONOMI YKPN | H18: MANAJEMEN / EKSEKUTIF (CEO/GM/MANAGER) | I18: LINGKUNGAN DAN ENERGI | K18: LAINNYA
B19: 35 (2019/2020) | D19: BANGLADESH | E19: KEPULAUAN RIAU | F19: STKIP ABDI WACANA WAMENA | H19: MAHASISWA / PELAJAR | I19: PERJALANAN DAN PARIWISATA
B20: 36 (2020/2021) | D20: BARBADOS | E20: LAMPUNG | F20: UNIVERSITAS AIRLANGGA | H20: LAINNYA | I20: HUKUM / JASA HUKUM
B21: 37 (2021/2022) | D21: BELANDA | E21: MALUKU | F21: UNIVERSITAS ANDALAS
B22: 38 (2022/2023) | D22: BELARUS | E22: MALUKU UTARA | F22: UNIVERSITAS ATMA JAYA YOGYAKARTA
B23: 39 (2023/2024) | D23: BELGIA | E23: NUSA TENGGARA BARAT | F23: UNIVERSITAS BANGKA BELITUNG
B24: 40 (2024/2025) | D24: BELIZE | E24: NUSA TENGGARA TIMUR | F24: UNIVERSITAS BENGKULU
D25: BENIN | E25: PAPUA | F25: UNIVERSITAS BINA NUSANTARA
D26: BHUTAN | E26: PAPUA BARAT | F26: UNIVERSITAS BORNEO TARAKAN
D27: BOLIVIA | E27: PAPUA BARAT DAYA | F27: UNIVERSITAS BRAWIJAYA
D28: BOSNIA DAN HERZEGOVINA | E28: PAPUA PEGUNUNGAN | F28: UNIVERSITAS CENDRAWASIH
D29: BOTSWANA | E29: PAPUA SELATAN | F29: UNIVERSITAS DIAN NUSWANTORO
D30: BRASIL | E30: PAPUA TENGAH | F30: UNIVERSITAS DIPONEGORO
D31: BRITANIA RAYA (INGGRIS) | E31: RIAU | F31: UNIVERSITAS HALU OLEO
D32: BRUNEI DARUSSALAM | E32: SULAWESI BARAT | F32: UNIVERSITAS ISLAM BANDUNG
D33: BULGARIA | E33: SULAWESI SELATAN | F33: UNIVERSITAS ISLAM MALANG
D34: BURKINA FASO | E34: SULAWESI TENGAH | F34: UNIVERSITAS ISLAM NEGERI SUNAN AMPEL
D35: BURUNDI | E35: SULAWESI TENGGARA | F35: UNIVERSITAS ISLAM NEGERI SUNAN GUNUNG DJATI
D36: CABO VERDE | E36: SULAWESI UTARA | F36: UNIVERSITAS ISLAM NEGERI SUNAN KALIJAGA
... D39: CHILI | E39: SUMATERA UTARA | F39: UNIVERSITAS JAMBI
D40: CHINA (TIONGKOK) | E40: =UPPER(Experiment!X40:X77) | F40: UNIVERSITAS JEMBER
D41: DENMARK | E41: =UPPER(Experiment!X41:X78) | F41: UNIVERSITAS JENDERAL ACHMAD YANI
D42: DJIBOUTI | E42: =UPPER(Experiment!X42:X79) | F42: UNIVERSITAS JENDERAL SOEDIRMAN
D43: DOMINIKA | E43: =UPPER(Experiment!X43:X80) | F43: UNIVERSITAS KATOLIK INDONESIA ATMA JAYA
D44: EKUADOR | E44: =UPPER(Experiment!X44:X81) | F44: UNIVERSITAS KATOLIK PARAHYANGAN
D45: EL SALVADOR | E45: =UPPER(Experiment!X45:X82) | F45: UNIVERSITAS KATOLIK SOEGIJAPRANATA
D46: ERITREA | E46: =UPPER(Experiment!X46:X83) | F46: UNIVERSITAS KATOLIK WIDYA MANDALA SURABAYA
D47: ESTONIA | E47: =UPPER(Experiment!X47:X84) | F47: UNIVERSITAS KHAIRUN
D48: ESWATINI | E48: =UPPER(Experiment!X48:X85) | F48: UNIVERSITAS KRISTEN DUTA WACANA
D49: ETHIOPIA | E49: =UPPER(Experiment!X49:X86) | F49: UNIVERSITAS KRISTEN MARANATHA
D50: FIJI | E50: =UPPER(Experiment!X50:X87) | F50: UNIVERSITAS KRISTEN PAPUA
D51: FILIPINA | E51: =UPPER(Experiment!X51:X88) | F51: UNIVERSITAS KRISTEN SATYA WACANA
... D103: MAKEDONIA UTARA | E103: =UPPER(Experiment!X103:X140) | F103: UNIVERSITAS WIDYATAMA
D104: MALADEWA | E104: =UPPER(Experiment!X104:X141)
D105: MALAWI | E105: =UPPER(Experiment!X105:X142)
D106: MALAYSIA | E106: =UPPER(Experiment!X106:X143)
D107: MALI | E107: =UPPER(Experiment!X107:X144)
D108: MALTA | E108: =UPPER(Experiment!X108:X145)
D109: MAROKO | E109: =UPPER(Experiment!X109:X146)
D110: MARSHALL (KEPULAUAN) | E110: =UPPER(Experiment!X110:X147)
D111: MAURITANIA | E111: =UPPER(Experiment!X111:X148)
D112: MAURITIUS | E112: =UPPER(Experiment!X112:X149)
D113: MEKSIKO | E113: =UPPER(Experiment!X113:X150)
D114: MESIR | E114: =UPPER(Experiment!X114:X151)
D115: MIKRONESIA | E115: =UPPER(Experiment!X115:X152)
... D195: ZIMBABWE | E195: =UPPER(Experiment!X195:X232)

Sheet Config
A1: Kolom A (Kunci) | B1: Kolom B (Nilai) | C1: Keterangan
A2: SHEET_NAME | B2: Database | C2: Nama Sheet Sumber Data Anggota
A3: DAILY_LIMIT | B3: 79 | C3: Batas maksimum email per hari
A4: DEFAULT_PIN | B4: 123123 | C4: PIN awal yang akan diinformasikan | D4: //FIX or Random seed?
A5: WEBSITE_LINK | B5: https://script.google.com/macros/s/AKfycbwFqxi5wvtTKNv37COGQWtr0WUrjmMICkMM5j1218s7Lk3FeU7HTCPR6Is1rL3cdcNA/exec | C5: Tautan website login
A6: NAMA_ORGANISASI | B6: Ikatan Alumni Djarum Beasiswa Plus | C6: Nama yang akan muncul di akhir email

Sheet Log_Pengiriman
A1: Waktu Pengiriman | B1: ID Anggota | C1: Email Tujuan | D1: Status | E1: Pesan Error/Keterangan
A2: 1/12/2025, 11.28.51 | B2: DBP00000000 | C2: halo.ikadbp@gmail.com | D2: TERKIRIM | E2: Berhasil dikirim.
A3: 1/12/2025, 11.30.44 | B3: DBP00000000 | C3: halo.ikadbp@gmail.com | D3: TERKIRIM | E3: Berhasil dikirim.
A4: 1/12/2025, 11.33.56 | B4: DBP00000000 | C4: halo.ikadbp@gmail.com | D4: TERKIRIM | E4: Berhasil dikirim.
A5: 17/12/2025, 17.57.37 | B5: DBP01000001 | C5: akbar.lawyer85@gmail.com | D5: TERKIRIM | E5: Berhasil dikirim.
A6: 17/12/2025, 17.57.38 | B6: DBP01000002 | C6: avgoenadi@gmail.com | D6: TERKIRIM | E6: Berhasil dikirim.
A7: 17/12/2025, 17.57.39 | B7: DBP01000003 | C7: gema.kusumaputri@gmail.com | D7: TERKIRIM | E7: Berhasil dikirim.
A8: 17/12/2025, 17.57.40 | B8: DBP01000004 | C8: putuagnia@gmail.com | D8: TERKIRIM | E8: Berhasil dikirim.
A9: 17/12/2025, 17.57.41 | B9: DBP01000005 | C9: dante.darmawangsa@upi.edu | D9: TERKIRIM | E9: Berhasil dikirim.
A10: 17/12/2025, 17.57.44 | B10: DBP01000006 | C10: ratri.mustikaning.h@gmail.com | D10: TERKIRIM | E10: Berhasil dikirim.
A11: 17/12/2025, 17.57.45 | B11: DBP01000007 | C11: puti.kemala.tanjung@gmail.com | D11: TERKIRIM | E11: Berhasil dikirim.
A12: 17/12/2025, 17.57.46 | B12: DBP01000008 | C12: roroajengtaufik@gmail.com | D12: TERKIRIM | E12: Berhasil dikirim.
... A21: 17/12/2025, 17.57.57 | B21: DBP01000017 | C21: nurrohmanazis1992@gmail.com | D21: TERKIRIM | E21: Berhasil dikirim.
A22: 17/12/2025, 17.57.58 | B22: DBP01000018 | D22: SKIP | E22: Email kosong atau format tidak valid.
A23: 17/12/2025, 17.57.58 | B23: DBP01000019 | C23: nicho.tarigan@gmail.com | D23: TERKIRIM | E23: Berhasil dikirim.
A24: 17/12/2025, 17.57.59 | B24: DBP01000020 | C24: Ogyfabrio@gmail.com | D24: TERKIRIM | E24: Berhasil dikirim.
A25: 17/12/2025, 17.58.00 | B25: DBP01000021 | C25: suhandies@gmail.com | D25: TERKIRIM | E25: Berhasil dikirim.
A26: 17/12/2025, 17.58.01 | B26: DBP01000022 | C26: riyadhi.atha@gmail.com | D26: TERKIRIM | E26: Berhasil dikirim.
A27: 17/12/2025, 17.58.04 | B27: DBP01000023 | C27: Marthanitaflorentinas@gmail.com | D27: TERKIRIM | E27: Berhasil dikirim.
A28: 17/12/2025, 17.58.05 | B28: DBP01000024 | C28: ferdinand.hiu@gmail.com | D28: TERKIRIM | E28: Berhasil dikirim.
A29: 17/12/2025, 17.58.06 | B29: DBP01000025 | C29: sagitas@xlfutureleaders.com | D29: TERKIRIM | E29: Berhasil dikirim.
A30: 17/12/2025, 17.58.07 | B30: DBP01000026 | C30: herozh94@gmail.com | D30: TERKIRIM | E30: Berhasil dikirim.
A31: 17/12/2025, 17.58.08 | B31: DBP01000027 | C31: Fjrhdy11@gmail.com | D31: TERKIRIM | E31: Berhasil dikirim.
A32: 17/12/2025, 17.58.09 | B32: DBP01000028 | C32: khasanm86@gmail.com | D32: TERKIRIM | E32: Berhasil dikirim.
A33: 17/12/2025, 17.58.10 | B33: DBP01000029 | C33: ilham.pbd@gmail.com | D33: TERKIRIM | E33: Berhasil dikirim.
A34: 17/12/2025, 17.58.11 | B34: DBP01000030 | C34: shafi.faris33@gmail.com | D34: TERKIRIM | E34: Berhasil dikirim.
... A39: 17/12/2025, 17.58.18 | B39: DBP01000035 | C39: yudith.tm@gmail.com | D39: TERKIRIM | E39: Berhasil dikirim.
A40: 17/12/2025, 17.58.20 | B40: DBP01000036 | D40: SKIP | E40: Email kosong atau format tidak valid.
A41: 17/12/2025, 17.58.20 | B41: DBP01000037 | C41: deidranataliet@gmail.com | D41: TERKIRIM | E41: Berhasil dikirim.
A42: 17/12/2025, 17.58.21 | B42: DBP01000038 | C42: dianboer@gmail.com | D42: TERKIRIM | E42: Berhasil dikirim.
A43: 17/12/2025, 17.58.22 | B43: DBP01000039 | C43: pelitawati1@gmail.com | D43: TERKIRIM | E43: Berhasil dikirim.
A44: 17/12/2025, 17.58.23 | B44: DBP01000040 | C44: ricohalim46@gmail.com | D44: TERKIRIM | E44: Berhasil dikirim.
A45: 17/12/2025, 17.58.24 | B45: DBP01000041 | C45: citra.asmara.83@gmail.com | D45: TERKIRIM | E45: Berhasil dikirim.
A46: 17/12/2025, 17.58.25 | B46: DBP01000042 | C46: cynthiakp.ckp@gmail.com | D46: TERKIRIM | E46: Berhasil dikirim.
A47: 17/12/2025, 17.58.26 | B47: DBP01000043 | C47: solehrifai@gmail.com | D47: TERKIRIM | E47: Berhasil dikirim.
A48: 17/12/2025, 17.58.29 | B48: DBP01000044 | C48: iqbalfa5@gmail.com | D48: TERKIRIM | E48: Berhasil dikirim.
A49: 17/12/2025, 17.58.30 | B49: DBP01000045 | C49: annisa.latu12@gmail.com | D49: TERKIRIM | E49: Berhasil dikirim.
A50: 17/12/2025, 17.58.31 | B50: DBP01000046 | C50: faizaldikky@gmail.com | D50: TERKIRIM | E50: Berhasil dikirim.
A51: 17/12/2025, 17.58.32 | B51: DBP01000047 | C51: veronicamdn9@gmail.com | D51: TERKIRIM | E51: Berhasil dikirim.
A52: 17/12/2025, 17.58.33 | B52: DBP01000048 | D52: SKIP | E52: Email kosong atau format tidak valid.
A53: 17/12/2025, 17.58.33 | B53: DBP01000049 | D53: SKIP | E53: Email kosong atau format tidak valid.
A54: 17/12/2025, 17.58.33 | B54: DBP01000050 | C54: pandusukmaks@gmail.com | D54: TERKIRIM | E54: Berhasil dikirim.
A55: 17/12/2025, 17.58.34 | B55: DBP01000051 | C55: yukaprm29@gmail.com | D55: TERKIRIM | E55: Berhasil dikirim.
A56: 17/12/2025, 17.58.35 | B56: DBP01000052 | C56: dudih.sutrisman@yahoo.co.id | D56: TERKIRIM | E56: Berhasil dikirim.
A57: 17/12/2025, 17.58.36 | B57: DBP01000053 | C57: baguz87@gmail.com | D57: TERKIRIM | E57: Berhasil dikirim.
A58: 17/12/2025, 17.58.39 | B58: DBP01000054 | C58: andreseptian227@gmail.com | D58: TERKIRIM | E58: Berhasil dikirim.
A59: 17/12/2025, 17.58.40 | B59: DBP01000055 | C59: uswachassanah@gmail.com | D59: TERKIRIM | E59: Berhasil dikirim.
A60: 17/12/2025, 17.58.41 | B60: DBP01000056 | C60: akbar.bayurahmat@gmail.com | D60: TERKIRIM | E60: Berhasil dikirim.
A61: 17/12/2025, 17.58.42 | B61: DBP01000057 | C61: Fitraarrahma12@gmail.com | D61: TERKIRIM | E61: Berhasil dikirim.
A62: 17/12/2025, 17.58.43 | B62: DBP01000058 | C62: nidya.hendrawan.tjong@gmail.com | D62: TERKIRIM | E62: Berhasil dikirim.
A63: 17/12/2025, 17.58.44 | B63: DBP01000059 | C63: ameliaaugustin00@gmail.com | D63: TERKIRIM | E63: Berhasil dikirim.
A64: 17/12/2025, 17.58.45 | B64: DBP01000060 | C64: farid.noor@umk.ac.id | D64: TERKIRIM | E64: Berhasil dikirim.
A65: 17/12/2025, 17.58.46 | B65: DBP01000061 | C65: shapangestu@gmail.com | D65: TERKIRIM | E65: Berhasil dikirim.
... A73: 17/12/2025, 17.58.58 | B73: DBP01000069 | C73: denirusmawan826@gmail.com | D73: TERKIRIM | E73: Berhasil dikirim.
A74: 17/12/2025, 17.58.59 | B74: DBP01000070 | D74: SKIP | E74: Email kosong atau format tidak valid.
A75: 17/12/2025, 17.58.59 | B75: DBP01000071 | C75: Elisabethevangeline31@gmail.com | D75: TERKIRIM | E75: Berhasil dikirim.
A76: 17/12/2025, 17.59.00 | B76: DBP01000072 | C76: intanlutviana39@gmail.com | D76: TERKIRIM | E76: Berhasil dikirim.
A77: 17/12/2025, 17.59.01 | B77: DBP01000073 | C77: annisatalmera@gmail.com | D77: TERKIRIM | E77: Berhasil dikirim.
A78: 17/12/2025, 17.59.04 | B78: DBP01000074 | C78: gabypanglylien@gmail.com | D78: TERKIRIM | E78: Berhasil dikirim.
A79: 17/12/2025, 17.59.05 | B79: DBP01000075 | C79: Putrasilaban691@gmail.com | D79: TERKIRIM | E79: Berhasil dikirim.
A80: 17/12/2025, 17.59.06 | B80: DBP01000076 | C80: suparmanwakidi.s.ak@gmail.com | D80: TERKIRIM | E80: Berhasil dikirim.
A81: 17/12/2025, 17.59.07 | B81: DBP01000077 | C81: dwipras88@gmail.com | D81: TERKIRIM | E81: Berhasil dikirim.
A82: 17/12/2025, 17.59.08 | B82: DBP01000078 | C82: budidennn@gmail.com | D82: TERKIRIM | E82: Berhasil dikirim.
A83: 17/12/2025, 17.59.09 | B83: DBP01000079 | C83: rizqullahrifqi22@gmail.com | D83: TERKIRIM | E83: Berhasil dikirim.

Sheet Experiment
A1: Jenis Pekerjaan | D1: Nama Instansi | L1: 18 | M1: 2002 | N1: 2003 | O1: =L1&" ("&M1&"/"&N1&")" -> 18 (2002/2003) | R1: No,Nama Negara,Benua | W1: No | X1: Nama Provinsi | Y1: Ibu Kota
A2: Profesional | D2: GURITNO and PARTNERS - Law Firm | H2: Laki-laki | I2: =UPPER(H2) -> LAKI-LAKI | L2: 19 | M2: 2003 | N2: 2004 | O2: =L2&" ("&M2&"/"&N2&")" -> 19 (2003/2004) | R2: 1,Afganistan,Asia | S2: =IFERROR(__xludf.DUMMYFUNCTION("SPLIT(R2,"","")"),1.0) -> 1 | T2: =IFERROR(__xludf.DUMMYFUNCTION("""COMPUTED_VALUE"""),"Afganistan") -> Afganistan | U2: =IFERROR(__xludf.DUMMYFUNCTION("""COMPUTED_VALUE"""),"Asia") -> Asia | W2: 1 | X2: Aceh | Y2: Banda Aceh | AA2: IAIN Kudus | AB2: =UPPER(AA2) -> IAIN KUDUS
A3: Pegawai Swasta | D3: PT. Parkland World Indonesia Jepara | H3: Laki-laki | I3: =UPPER(H3) -> LAKI-LAKI | L3: 20 | M3: 2004 | N3: 2005 | O3: =L3&" ("&M3&"/"&N3&")" -> 20 (2004/2005) | R3: 2,Afrika Selatan,Afrika | S3: =IFERROR(__xludf.DUMMYFUNCTION("SPLIT(R3,"","")"),2.0) -> 2 | T3: =IFERROR(__xludf.DUMMYFUNCTION("""COMPUTED_VALUE"""),"Afrika Selatan") -> Afrika Selatan | U3: =IFERROR(__xludf.DUMMYFUNCTION("""COMPUTED_VALUE"""),"Afrika") -> Afrika | W3: 2 | X3: Bali | Y3: Denpasar | AA3: Institut Kesenian Jakarta | AB3: =UPPER(AA3) -> INSTITUT KESENIAN JAKARTA
A4: Pegawai Swasta | D4: PT. Nutrifood | H4: Perempuan | I4: =UPPER(H4) -> PEREMPUAN | L4: 21 | M4: 2005 | N4: 2006 | O4: =L4&" ("&M4&"/"&N4&")" -> 21 (2005/2006) | R4: 3,Albania,Eropa | S4: =IFERROR(__xludf.DUMMYFUNCTION("SPLIT(R4,"","")"),3.0) -> 3 | T4: =IFERROR(__xludf.DUMMYFUNCTION("""COMPUTED_VALUE"""),"Albania") -> Albania | U4: =IFERROR(__xludf.DUMMYFUNCTION("""COMPUTED_VALUE"""),"Eropa") -> Eropa | W4: 3 | X4: Banten | Y4: Serang | AA4: Institut Pertanian Bogor | AB4: =UPPER(AA4) -> INSTITUT PERTANIAN BOGOR
A5: Pegawai Swasta | D5: PT. PRIMA AGRO TECH | H5: Perempuan | I5: =UPPER(H5) -> PEREMPUAN | L5: 22 | M5: 2006 | N5: 2007 | O5: =L5&" ("&M5&"/"&N5&")" -> 22 (2006/2007) | R5: 4,Aljazair,Afrika | S5: =IFERROR(__xludf.DUMMYFUNCTION("SPLIT(R5,"","")"),4.0) -> 4 | T5: =IFERROR(__xludf.DUMMYFUNCTION("""COMPUTED_VALUE"""),"Aljazair") -> Aljazair | U5: =IFERROR(__xludf.DUMMYFUNCTION("""COMPUTED_VALUE"""),"Afrika") -> Afrika | W5: 4 | X5: Bengkulu | Y5: Bengkulu | AA5: Institut Seni Indonesia Yogyakarta | AB5: =UPPER(AA5) -> INSTITUT SENI INDONESIA YOGYAKARTA
A6: BUMN/Pemerintahan(PNS) | D6: PT. Bank Negara Indonesia (Persero), Tbk | H6: Laki-laki | I6: =UPPER(H6) -> LAKI-LAKI | L6: 23 | M6: 2007 | N6: 2008 | O6: =L6&" ("&M6&"/"&N6&")" -> 23 (2007/2008) | R6: 5,Amerika Serikat,Amerika Utara | S6: =IFERROR(__xludf.DUMMYFUNCTION("SPLIT(R6,"","")"),5.0) -> 5 | T6: =IFERROR(__xludf.DUMMYFUNCTION("""COMPUTED_VALUE"""),"Amerika Serikat") -> Amerika Serikat | U6: =IFERROR(__xludf.DUMMYFUNCTION("""COMPUTED_VALUE"""),"Amerika Utara") -> Amerika Utara | W6: 5 | X6: DI Yogyakarta | Y6: Yogyakarta | AA6: Institut Teknologi Bandung | AB6: =UPPER(AA6) -> INSTITUT TEKNOLOGI BANDUNG
A7: Wiraswasta | D7: Companera Business & Companera Apparel | H7: Perempuan | I7: =UPPER(H7) -> PEREMPUAN | L7: 24 | M7: 2008 | N7: 2009 | O7: =L7&" ("&M7&"/"&N7&")" -> 24 (2008/2009) | R7: 6,Andorra,Eropa | S7: =IFERROR(__xludf.DUMMYFUNCTION("SPLIT(R7,"","")"),6.0) -> 6 | T7: =IFERROR(__xludf.DUMMYFUNCTION("""COMPUTED_VALUE"""),"Andorra") -> Andorra | U7: =IFERROR(__xludf.DUMMYFUNCTION("""COMPUTED_VALUE"""),"Eropa") -> Eropa | W7: 6 | X7: DKI Jakarta | Y7: Jakarta | AA7: Institut Teknologi Harapan Bangsa | AB7: =UPPER(AA7) -> INSTITUT TEKNOLOGI HARAPAN BANGSA
A8: Pegawai Swasta | D8: PT. Home center indonesia (kawan lama group) | H8: Perempuan | I8: =UPPER(H8) -> PEREMPUAN | L8: 25 | M8: 2009 | N8: 2010 | O8: =L8&" ("&M8&"/"&N8&")" -> 25 (2009/2010) | R8: 7,Angola,Afrika | S8: =IFERROR(__xludf.DUMMYFUNCTION("SPLIT(R8,"","")"),7.0) -> 7 | T8: =IFERROR(__xludf.DUMMYFUNCTION("""COMPUTED_VALUE"""),"Angola") -> Angola | U8: =IFERROR(__xludf.DUMMYFUNCTION("""COMPUTED_VALUE"""),"Afrika") -> Afrika | W8: 7 | X8: Gorontalo | Y8: Gorontalo | AA8: Institut Teknologi Kalimantan | AB8: =UPPER(AA8) -> INSTITUT TEKNOLOGI KALIMANTAN
A9: Belum Bekerja | D9: Belum Bekerja | H9: Perempuan | I9: =UPPER(H9) -> PEREMPUAN | L9: 26 | M9: 2010 | N9: 2011 | O9: =L9&" ("&M9&"/"&N9&")" -> 26 (2010/2011) | R9: 8,Antigua dan Barbuda,Amerika Utara | S9: =IFERROR(__xludf.DUMMYFUNCTION("SPLIT(R9,"","")"),8.0) -> 8 | T9: =IFERROR(__xludf.DUMMYFUNCTION("""COMPUTED_VALUE"""),"Antigua dan Barbuda") -> Antigua dan Barbuda | U9: =IFERROR(__xludf.DUMMYFUNCTION("""COMPUTED_VALUE"""),"Amerika Utara") -> Amerika Utara | W9: 8 | X9: Jambi | Y9: Jambi | AA9: Institut Teknologi Nasional | AB9: =UPPER(AA9) -> INSTITUT TEKNOLOGI NASIONAL
A10: Pegawai Swasta | D10: Astra International - Toyota Auto2000 | H10: Laki-laki | I10: =UPPER(H10) -> LAKI-LAKI | L10: 27 | M10: 2011 | N10: 2012 | O10: =L10&" ("&M10&"/"&N10&")" -> 27 (2011/2012) | R10: 9,Arab Saudi,Asia | S10: =IFERROR(__xludf.DUMMYFUNCTION("SPLIT(R10,"","")"),9.0) -> 9 | T10: =IFERROR(__xludf.DUMMYFUNCTION("""COMPUTED_VALUE"""),"Arab Saudi") -> Arab Saudi | U10: =IFERROR(__xludf.DUMMYFUNCTION("""COMPUTED_VALUE"""),"Asia") -> Asia | W10: 9 | X10: Jawa Barat | Y10: Bandung | AA10: Institut Teknologi Sepuluh Nopember | AB10: =UPPER(AA10) -> INSTITUT TEKNOLOGI SEPULUH NOPEMBER
A11: BUMN/Pemerintahan(PNS) | D11: PT PLN INDONESIA POWER | H11: Laki-laki | I11: =UPPER(H11) -> LAKI-LAKI | L11: 28 | M11: 2012 | N11: 2013 | O11: =L11&" ("&M11&"/"&N11&")" -> 28 (2012/2013) | R11: 10,Argentina,Amerika Selatan | S11: =IFERROR(__xludf.DUMMYFUNCTION("SPLIT(R11,"","")"),10.0) -> 10 | T11: =IFERROR(__xludf.DUMMYFUNCTION("""COMPUTED_VALUE"""),"Argentina") -> Argentina | U11: =IFERROR(__xludf.DUMMYFUNCTION("""COMPUTED_VALUE"""),"Amerika Selatan") -> Amerika Selatan | W11: 10 | X11: Jawa Tengah | Y11: Semarang | AA11: Politeknik Elektronika Negeri Surabaya | AB11: =UPPER(AA11) -> POLITEKNIK ELEKTRONIKA NEGERI SURABAYA
A12: Pegawai Swasta | D12: MarkPlus | H12: Laki-laki | I12: =UPPER(H12) -> LAKI-LAKI | L12: 29 | M12: 2013 | N12: 2014 | O12: =L12&" ("&M12&"/"&N12&")" -> 29 (2013/2014) | R12: 11,Armenia,Asia | S12: =IFERROR(__xludf.DUMMYFUNCTION("SPLIT(R12,"","")"),11.0) -> 11 | T12: =IFERROR(__xludf.DUMMYFUNCTION("""COMPUTED_VALUE"""),"Armenia") -> Armenia | U12: =IFERROR(__xludf.DUMMYFUNCTION("""COMPUTED_VALUE"""),"Asia") -> Asia | W12: 11 | X12: Jawa Timur | Y12: Surabaya | AA12: Politeknik Negeri Bandung | AB12: =UPPER(AA12) -> POLITEKNIK NEGERI BANDUNG
A13: Mahasiswa | D13: Belum Bekerja | H13: Laki-laki | I13: =UPPER(H13) -> LAKI-LAKI | L13: 30 | M13: 2014 | N13: 2015 | O13: =L13&" ("&M13&"/"&N13&")" -> 30 (2014/2015) | R13: 12,Australia,Australia/Oceania | S13: =IFERROR(__xludf.DUMMYFUNCTION("SPLIT(R13,"","")"),12.0) -> 12 | T13: =IFERROR(__xludf.DUMMYFUNCTION("""COMPUTED_VALUE"""),"Australia") -> Australia | U13: =IFERROR(__xludf.DUMMYFUNCTION("""COMPUTED_VALUE"""),"Australia/Oceania") -> Australia/Oceania | W13: 12 | X13: Kalimantan Barat | Y13: Pontianak | AA13: Politeknik Negeri Batam | AB13: =UPPER(AA13) -> POLITEKNIK NEGERI BATAM
A14: Pegawai Swasta | D14: Yayasan Rumah Energi | H14: Perempuan | I14: =UPPER(H14) -> PEREMPUAN | L14: 31 | M14: 2015 | N14: 2016 | O14: =L14&" ("&M14&"/"&N14&")" -> 31 (2015/2016) | R14: 13,Austria,Eropa | S14: =IFERROR(__xludf.DUMMYFUNCTION("SPLIT(R14,"","")"),13.0) -> 13 | T14: =IFERROR(__xludf.DUMMYFUNCTION("""COMPUTED_VALUE"""),"Austria") -> Austria | U14: =IFERROR(__xludf.DUMMYFUNCTION("""COMPUTED_VALUE"""),"Eropa") -> Eropa | W14: 13 | X14: Kalimantan Selatan | Y14: Banjarbaru | AA14: Politeknik Negeri Malang | AB14: =UPPER(AA14) -> POLITEKNIK NEGERI MALANG
A15: Pegawai Swasta | D15: PT YUKBISNIS INDONESIA | H15: Laki-laki | I15: =UPPER(H15) -> LAKI-LAKI | L15: 32 | M15: 2016 | N15: 2017 | O15: =L15&" ("&M15&"/"&N15&")" -> 32 (2016/2017) | R15: 14,Azerbaijan,Asia | S15: =IFERROR(__xludf.DUMMYFUNCTION("SPLIT(R15,"","")"),14.0) -> 14 | T15: =IFERROR(__xludf.DUMMYFUNCTION("""COMPUTED_VALUE"""),"Azerbaijan") -> Azerbaijan | U15: =IFERROR(__xludf.DUMMYFUNCTION("""COMPUTED_VALUE"""),"Asia") -> Asia | W15: 14 | X15: Kalimantan Tengah | Y15: Palangka Raya | AA15: Politeknik Negeri Samarinda | AB15: =UPPER(AA15) -> POLITEKNIK NEGERI SAMARINDA
A16: Pegawai Swasta | D16: PT.Grab Teknologi Indonesia | H16: Perempuan | I16: =UPPER(H16) -> PEREMPUAN | L16: 33 | M16: 2017 | N16: 2018 | O16: =L16&" ("&M16&"/"&N16&")" -> 33 (2017/2018) | R16: 15,Bahama,Amerika Utara | S16: =IFERROR(__xludf.DUMMYFUNCTION("SPLIT(R16,"","")"),15.0) -> 15 | T16: =IFERROR(__xludf.DUMMYFUNCTION("""COMPUTED_VALUE"""),"Bahama") -> Bahama | U16: =IFERROR(__xludf.DUMMYFUNCTION("""COMPUTED_VALUE"""),"Amerika Utara") -> Amerika Utara | W16: 15 | X16: Kalimantan Timur | Y16: Samarinda | AA16: Politeknik Negeri Semarang | AB16: =UPPER(AA16) -> POLITEKNIK NEGERI SEMARANG
A17: BUMN/Pemerintahan(PNS) | D17: Bank Mandiri | H17: Laki-laki | I17: =UPPER(H17) -> LAKI-LAKI | L17: 34 | M17: 2018 | N17: 2019 | O17: =L17&" ("&M17&"/"&N17&")" -> 34 (2018/2019) | R17: 16,Bahrain,Asia | S17: =IFERROR(__xludf.DUMMYFUNCTION("SPLIT(R17,"","")"),16.0) -> 16 | T17: =IFERROR(__xludf.DUMMYFUNCTION("""COMPUTED_VALUE"""),"Bahrain") -> Bahrain | U17: =IFERROR(__xludf.DUMMYFUNCTION("""COMPUTED_VALUE"""),"Asia") -> Asia | W17: 16 | X17: Kalimantan Utara | Y17: Tanjung Selor | AA17: Sekolah Tinggi Ilmu Ekonomi Malangkucecwara | AB17: =UPPER(AA17) -> SEKOLAH TINGGI ILMU EKONOMI MALANGKUCECWARA
A18: BUMN/Pemerintahan(PNS) | D18: PT. Bank Mandiri (Persero) Tbk | H18: Laki-laki | I18: =UPPER(H18) -> LAKI-LAKI | L18: 35 | M18: 2019 | N18: 2020 | O18: =L18&" ("&M18&"/"&N18&")" -> 35 (2019/2020) | R18: 17,Bangladesh,Asia | S18: =IFERROR(__xludf.DUMMYFUNCTION("SPLIT(R18,"","")"),17.0) -> 17 | T18: =IFERROR(__xludf.DUMMYFUNCTION("""COMPUTED_VALUE"""),"Bangladesh") -> Bangladesh | U18: =IFERROR(__xludf.DUMMYFUNCTION("""COMPUTED_VALUE"""),"Asia") -> Asia | W18: 17 | X18: Kepulauan Bangka Belitung | Y18: Pangkal Pinang | AA18: Sekolah Tinggi Ilmu Ekonomi YKPN | AB18: =UPPER(AA18) -> SEKOLAH TINGGI ILMU EKONOMI YKPN
A19: Dosen | D19: Institut Seni Budaya Indonesia Aceh | H19: Laki-laki | I19: =UPPER(H19) -> LAKI-LAKI | L19: 36 | M19: 2020 | N19: 2021 | O19: =L19&" ("&M19&"/"&N19&")" -> 36 (2020/2021) | R19: 18,Barbados,Amerika Utara | S19: =IFERROR(__xludf.DUMMYFUNCTION("SPLIT(R19,"","")"),18.0) -> 18 | T19: =IFERROR(__xludf.DUMMYFUNCTION("""COMPUTED_VALUE"""),"Barbados") -> Barbados | U19: =IFERROR(__xludf.DUMMYFUNCTION("""COMPUTED_VALUE"""),"Amerika Utara") -> Amerika Utara | W19: 18 | X19: Kepulauan Riau | Y19: Tanjung Pinang | AA19: STKIP Abdi Wacana Wamena | AB19: =UPPER(AA19) -> STKIP ABDI WACANA WAMENA
A20: Pegawai Swasta | D20: PT. Fortius Solusi Informatika | H20: Laki-laki | I20: =UPPER(H20) -> LAKI-LAKI | L20: 37 | M20: 2021 | N20: 2022 | O20: =L20&" ("&M20&"/"&N20&")" -> 37 (2021/2022) | R20: 19,Belanda,Eropa | S20: =IFERROR(__xludf.DUMMYFUNCTION("SPLIT(R20,"","")"),19.0) -> 19 | T20: =IFERROR(__xludf.DUMMYFUNCTION("""COMPUTED_VALUE"""),"Belanda") -> Belanda | U20: =IFERROR(__xludf.DUMMYFUNCTION("""COMPUTED_VALUE"""),"Eropa") -> Eropa | W20: 19 | X20: Lampung | Y20: Bandar Lampung | AA20: Universitas Airlangga | AB20: =UPPER(AA20) -> UNIVERSITAS AIRLANGGA
A21: Coding Tutor | D21: Algorithmics Indonesia dan Timedoor Academy | H21: Laki-laki | I21: =UPPER(H21) -> LAKI-LAKI | L21: 38 | M21: 2022 | N21: 2023 | O21: =L21&" ("&M21&"/"&N21&")" -> 38 (2022/2023) | R21: 20,Belarus,Eropa | S21: =IFERROR(__xludf.DUMMYFUNCTION("SPLIT(R21,"","")"),20.0) -> 20 | T21: =IFERROR(__xludf.DUMMYFUNCTION("""COMPUTED_VALUE"""),"Belarus") -> Belarus | U21: =IFERROR(__xludf.DUMMYFUNCTION("""COMPUTED_VALUE"""),"Eropa") -> Eropa | W21: 20 | X21: Maluku | Y21: Ambon | AA21: Universitas Andalas | AB21: =UPPER(AA21) -> UNIVERSITAS ANDALAS
A22: Pegawai Swasta | D22: KAP Parker Russell Indonesia | H22: Laki-laki | I22: =UPPER(H22) -> LAKI-LAKI | L22: 39 | M22: 2023 | N22: 2024 | O22: =L22&" ("&M22&"/"&N22&")" -> 39 (2023/2024) | R22: 21,Belgia,Eropa | S22: =IFERROR(__xludf.DUMMYFUNCTION("SPLIT(R22,"","")"),21.0) -> 21 | T22: =IFERROR(__xludf.DUMMYFUNCTION("""COMPUTED_VALUE"""),"Belgia") -> Belgia | U22: =IFERROR(__xludf.DUMMYFUNCTION("""COMPUTED_VALUE"""),"Eropa") -> Eropa | W22: 21 | X22: Maluku Utara | Y22: Sofifi | AA22: Universitas Atma Jaya Yogyakarta | AB22: =UPPER(AA22) -> UNIVERSITAS ATMA JAYA YOGYAKARTA
A23: Pegawai Swasta | D23: PT. Indonesia Epson Industry | H23: Perempuan | I23: =UPPER(H23) -> PEREMPUAN | L23: 40 | M23: 2024 | N23: 2025 | O23: =L23&" ("&M23&"/"&N23&")" -> 40 (2024/2025) | R23: 22,Belize,Amerika Utara | S23: =IFERROR(__xludf.DUMMYFUNCTION("SPLIT(R23,"","")"),22.0) -> 22 | T23: =IFERROR(__xludf.DUMMYFUNCTION("""COMPUTED_VALUE"""),"Belize") -> Belize | U23: =IFERROR(__xludf.DUMMYFUNCTION("""COMPUTED_VALUE"""),"Amerika Utara") -> Amerika Utara | W23: 22 | X23: Nusa Tenggara Barat | Y23: Mataram | AA23: Universitas Bangka Belitung | AB23: =UPPER(AA23) -> UNIVERSITAS BANGKA BELITUNG
A24: Mahasiswa | D24: Universitas Muria Kudus | H24: Laki-laki | I24: =UPPER(H24) -> LAKI-LAKI | R24: 23,Benin,Afrika | S24: =IFERROR(__xludf.DUMMYFUNCTION("SPLIT(R24,"","")"),23.0) -> 23 | T24: =IFERROR(__xludf.DUMMYFUNCTION("""COMPUTED_VALUE"""),"Benin") -> Benin | U24: =IFERROR(__xludf.DUMMYFUNCTION("""COMPUTED_VALUE"""),"Afrika") -> Afrika | W24: 23 | X24: Nusa Tenggara Timur | Y24: Kupang | AA24: Universitas Bengkulu | AB24: =UPPER(AA24) -> UNIVERSITAS BENGKULU
A25: Belum Bekerja | D25: Belum Bekerja | H25: Perempuan | I25: =UPPER(H25) -> PEREMPUAN | R25: 24,Bhutan,Asia | S25: =IFERROR(__xludf.DUMMYFUNCTION("SPLIT(R25,"","")"),24.0) -> 24 | T25: =IFERROR(__xludf.DUMMYFUNCTION("""COMPUTED_VALUE"""),"Bhutan") -> Bhutan | U25: =IFERROR(__xludf.DUMMYFUNCTION("""COMPUTED_VALUE"""),"Asia") -> Asia | W25: 24 | X25: Papua | Y25: Jayapura | AA25: Universitas Bina Nusantara | AB25: =UPPER(AA25) -> UNIVERSITAS BINA NUSANTARA
A26: Guru PPPK | D26: SMP Negeri 1 Pageruyung | H26: Laki-laki | I26: =UPPER(H26) -> LAKI-LAKI | R26: 25,Bolivia,Amerika Selatan | S26: =IFERROR(__xludf.DUMMYFUNCTION("SPLIT(R26,"","")"),25.0) -> 25 | T26: =IFERROR(__xludf.DUMMYFUNCTION("""COMPUTED_VALUE"""),"Bolivia") -> Bolivia | U26: =IFERROR(__xludf.DUMMYFUNCTION("""COMPUTED_VALUE"""),"Amerika Selatan") -> Amerika Selatan | W26: 25 | X26: Papua Barat | Y26: Manokwari | AA26: Universitas Borneo Tarakan | AB26: =UPPER(AA26) -> UNIVERSITAS BORNEO TARAKAN
A27: Pegawai Swasta | D27: PT Datacomm Diangraha | H27: Laki-laki | I27: =UPPER(H27) -> LAKI-LAKI | R27: 26,Bosnia dan Herzegovina,Eropa | S27: =IFERROR(__xludf.DUMMYFUNCTION("SPLIT(R27,"","")"),26.0) -> 26 | T27: =IFERROR(__xludf.DUMMYFUNCTION("""COMPUTED_VALUE"""),"Bosnia dan Herzegovina") -> Bosnia dan Herzegovina | U27: =IFERROR(__xludf.DUMMYFUNCTION("""COMPUTED_VALUE"""),"Eropa") -> Eropa | W27: 26 | X27: Papua Barat Daya | Y27: Sorong | AA27: Universitas Brawijaya | AB27: =UPPER(AA27) -> UNIVERSITAS BRAWIJAYA
A28: Pegawai Swasta | D28: BCA Finance | H28: Laki-laki | I28: =UPPER(H28) -> LAKI-LAKI | R28: 27,Botswana,Afrika | S28: =IFERROR(__xludf.DUMMYFUNCTION("SPLIT(R28,"","")"),27.0) -> 27 | T28: =IFERROR(__xludf.DUMMYFUNCTION("""COMPUTED_VALUE"""),"Botswana") -> Botswana | U28: =IFERROR(__xludf.DUMMYFUNCTION("""COMPUTED_VALUE"""),"Afrika") -> Afrika | W28: 27 | X28: Papua Pegunungan | Y28: Wamena | AA28: Universitas Cendrawasih | AB28: =UPPER(AA28) -> UNIVERSITAS CENDRAWASIH
A29: Wiraswasta | D29: PT Zurich Topas Life | H29: Laki-laki | I29: =UPPER(H29) -> LAKI-LAKI | R29: 28,Brasil,Amerika Selatan | S29: =IFERROR(__xludf.DUMMYFUNCTION("SPLIT(R29,"","")"),28.0) -> 28 | T29: =IFERROR(__xludf.DUMMYFUNCTION("""COMPUTED_VALUE"""),"Brasil") -> Brasil | U29: =IFERROR(__xludf.DUMMYFUNCTION("""COMPUTED_VALUE"""),"Amerika Selatan") -> Amerika Selatan | W29: 28 | X29: Papua Selatan | Y29: Merauke | AA29: Universitas Dian Nuswantoro | AB29: =UPPER(AA29) -> UNIVERSITAS DIAN NUSWANTORO
A30: Freelance | D30: Hotel 1O1 Urban Jakarta Thamrin | H30: Laki-laki | I30: =UPPER(H30) -> LAKI-LAKI | R30: 29,Britania Raya (Inggris),Eropa | S30: =IFERROR(__xludf.DUMMYFUNCTION("SPLIT(R30,"","")"),29.0) -> 29 | T30: =IFERROR(__xludf.DUMMYFUNCTION("""COMPUTED_VALUE"""),"Britania Raya (Inggris)") -> Britania Raya (Inggris) | U30: =IFERROR(__xludf.DUMMYFUNCTION("""COMPUTED_VALUE"""),"Eropa") -> Eropa | W30: 29 | X30: Papua Tengah | Y30: Nabire | AA30: Universitas Diponegoro | AB30: =UPPER(AA30) -> UNIVERSITAS DIPONEGORO
A31: Pegawai Swasta | D31: Motasa Indonesia | H31: Perempuan | I31: =UPPER(H31) -> PEREMPUAN | R31: 30,Brunei Darussalam,Asia | S31: =IFERROR(__xludf.DUMMYFUNCTION("SPLIT(R31,"","")"),30.0) -> 30 | T31: =IFERROR(__xludf.DUMMYFUNCTION("""COMPUTED_VALUE"""),"Brunei Darussalam") -> Brunei Darussalam | U31: =IFERROR(__xludf.DUMMYFUNCTION("""COMPUTED_VALUE"""),"Asia") -> Asia | W31: 30 | X31: Riau | Y31: Pekanbaru | AA31: Universitas Halu Oleo | AB31: =UPPER(AA31) -> UNIVERSITAS HALU OLEO
A32: Pegawai Swasta | D32: PT Geotronix Pratama Indonesia | H32: Perempuan | I32: =UPPER(H32) -> PEREMPUAN | R32: 31,Bulgaria,Eropa | S32: =IFERROR(__xludf.DUMMYFUNCTION("SPLIT(R32,"","")"),31.0) -> 31 | T32: =IFERROR(__xludf.DUMMYFUNCTION("""COMPUTED_VALUE"""),"Bulgaria") -> Bulgaria | U32: =IFERROR(__xludf.DUMMYFUNCTION("""COMPUTED_VALUE"""),"Eropa") -> Eropa | W32: 31 | X32: Sulawesi Barat | Y32: Mamuju | AA32: Universitas Islam Bandung | AB32: =UPPER(AA32) -> UNIVERSITAS ISLAM BANDUNG
A33: Pegawai Swasta | D33: PT Adlink Sinemedia Indonesia | H33: Perempuan | I33: =UPPER(H33) -> PEREMPUAN | R33: 32,Burkina Faso,Afrika | S33: =IFERROR(__xludf.DUMMYFUNCTION("SPLIT(R33,"","")"),32.0) -> 32 | T33: =IFERROR(__xludf.DUMMYFUNCTION("""COMPUTED_VALUE"""),"Burkina Faso") -> Burkina Faso | U33: =IFERROR(__xludf.DUMMYFUNCTION("""COMPUTED_VALUE"""),"Afrika") -> Afrika | W33: 32 | X33: Sulawesi Selatan | Y33: Makassar | AA33: Universitas Islam Malang | AB33: =UPPER(AA33) -> UNIVERSITAS ISLAM MALANG
A34: BUMN/Pemerintahan(PNS) | D34: PT. Bank Rakyat Indonesia Tbk. | H34: Perempuan | I34: =UPPER(H34) -> PEREMPUAN | R34: 33,Burundi,Afrika | S34: =IFERROR(__xludf.DUMMYFUNCTION("SPLIT(R34,"","")"),33.0) -> 33 | T34: =IFERROR(__xludf.DUMMYFUNCTION("""COMPUTED_VALUE"""),"Burundi") -> Burundi | U34: =IFERROR(__xludf.DUMMYFUNCTION("""COMPUTED_VALUE"""),"Afrika") -> Afrika | W34: 33 | X34: Sulawesi Tengah | Y34: Palu | AA34: Universitas Islam Negeri Sunan Ampel | AB34: =UPPER(AA34) -> UNIVERSITAS ISLAM NEGERI SUNAN AMPEL
A35: Dosen | D35: Universitas Mulawarman | H35: Perempuan | I35: =UPPER(H35) -> PEREMPUAN | R35: 34,Cabo Verde,Afrika | S35: =IFERROR(__xludf.DUMMYFUNCTION("SPLIT(R35,"","")"),34.0) -> 34 | T35: =IFERROR(__xludf.DUMMYFUNCTION("""COMPUTED_VALUE"""),"Cabo Verde") -> Cabo Verde | U35: =IFERROR(__xludf.DUMMYFUNCTION("""COMPUTED_VALUE"""),"Afrika") -> Afrika | W35: 34 | X35: Sulawesi Tenggara | Y35: Kendari | AA35: Universitas Islam Negeri Sunan Gunung Djati | AB35: =UPPER(AA35) -> UNIVERSITAS ISLAM NEGERI SUNAN GUNUNG DJATI
A36: Pegawai Swasta | D36: Ubiklan | H36: Laki-laki | I36: =UPPER(H36) -> LAKI-LAKI | R36: 35,Ceko (Republik Ceko),Eropa | S36: =IFERROR(__xludf.DUMMYFUNCTION("SPLIT(R36,"","")"),35.0) -> 35 | T36: =IFERROR(__xludf.DUMMYFUNCTION("""COMPUTED_VALUE"""),"Ceko (Republik Ceko)") -> Ceko (Republik Ceko) | U36: =IFERROR(__xludf.DUMMYFUNCTION("""COMPUTED_VALUE"""),"Eropa") -> Eropa | W36: 35 | X36: Sulawesi Utara | Y36: Manado | AA36: Universitas Islam Negeri Sunan Kalijaga | AB36: =UPPER(AA36) -> UNIVERSITAS ISLAM NEGERI SUNAN KALIJAGA
A37: Belum Bekerja | D37: Belum Bekerja | H37: Perempuan | I37: =UPPER(H37) -> PEREMPUAN | R37: 36,Chad,Afrika | S37: =IFERROR(__xludf.DUMMYFUNCTION("SPLIT(R37,"","")"),36.0) -> 36 | T37: =IFERROR(__xludf.DUMMYFUNCTION("""COMPUTED_VALUE"""),"Chad") -> Chad | U37: =IFERROR(__xludf.DUMMYFUNCTION("""COMPUTED_VALUE"""),"Afrika") -> Afrika | W37: 36 | X37: Sumatera Barat | Y37: Padang | AA37: Universitas Islam Negeri Syarif Hidayatullah | AB37: =UPPER(AA37) -> UNIVERSITAS ISLAM NEGERI SYARIF HIDAYATULLAH
A38: Pegawai Swasta | D38: PT Bumibaru | H38: Laki-laki | I38: =UPPER(H38) -> LAKI-LAKI | R38: 37,Chili,Amerika Selatan | S38: =IFERROR(__xludf.DUMMYFUNCTION("SPLIT(R38,"","")"),37.0) -> 37 | T38: =IFERROR(__xludf.DUMMYFUNCTION("""COMPUTED_VALUE"""),"Chili") -> Chili | U38: =IFERROR(__xludf.DUMMYFUNCTION("""COMPUTED_VALUE"""),"Amerika Selatan") -> Amerika Selatan | W38: 37 | X38: Sumatera Selatan | Y38: Palembang | AA38: Universitas Islam Negeri Walisongo | AB38: =UPPER(AA38) -> UNIVERSITAS ISLAM NEGERI WALISONGO
A39: Pegawai Swasta | D39: McKinsey and Company | H39: Perempuan | I39: =UPPER(H39) -> PEREMPUAN | R39: 38,China (Tiongkok),Asia | S39: =IFERROR(__xludf.DUMMYFUNCTION("SPLIT(R39,"","")"),38.0) -> 38 | T39: =IFERROR(__xludf.DUMMYFUNCTION("""COMPUTED_VALUE"""),"China (Tiongkok)") -> China (Tiongkok) | U39: =IFERROR(__xludf.DUMMYFUNCTION("""COMPUTED_VALUE"""),"Asia") -> Asia | W39: 38 | X39: Sumatera Utara | Y39: Medan | AA39: Universitas Jambi | AB39: =UPPER(AA39) -> UNIVERSITAS JAMBI
A40: BUMN/Pemerintahan(PNS) | D40: Kementerian Hukum dan HAM | H40: Perempuan | I40: =UPPER(H40) -> PEREMPUAN | R40: 39,Denmark,Eropa | S40: =IFERROR(__xludf.DUMMYFUNCTION("SPLIT(R40,"","")"),39.0) -> 39 | T40: =IFERROR(__xludf.DUMMYFUNCTION("""COMPUTED_VALUE"""),"Denmark") -> Denmark | U40: =IFERROR(__xludf.DUMMYFUNCTION("""COMPUTED_VALUE"""),"Eropa") -> Eropa | AA40: Universitas Jember | AB40: =UPPER(AA40) -> UNIVERSITAS JEMBER
A41: Pegawai Swasta | D41: PT. Accenture | H41: Laki-laki | I41: =UPPER(H41) -> LAKI-LAKI | R41: 40,Djibouti,Afrika | S41: =IFERROR(__xludf.DUMMYFUNCTION("SPLIT(R41,"","")"),40.0) -> 40 | T41: =IFERROR(__xludf.DUMMYFUNCTION("""COMPUTED_VALUE"""),"Djibouti") -> Djibouti | U41: =IFERROR(__xludf.DUMMYFUNCTION("""COMPUTED_VALUE"""),"Afrika") -> Afrika | AA41: Universitas Jenderal Achmad Yani | AB41: =UPPER(AA41) -> UNIVERSITAS JENDERAL ACHMAD YANI
A42: BUMN/Pemerintahan(PNS) | D42: Institut Teknologi Bandung | H42: Laki-laki | I42: =UPPER(H42) -> LAKI-LAKI | R42: 41,Dominika,Amerika Utara | S42: =IFERROR(__xludf.DUMMYFUNCTION("SPLIT(R42,"","")"),41.0) -> 41 | T42: =IFERROR(__xludf.DUMMYFUNCTION("""COMPUTED_VALUE"""),"Dominika") -> Dominika | U42: =IFERROR(__xludf.DUMMYFUNCTION("""COMPUTED_VALUE"""),"Amerika Utara") -> Amerika Utara | AA42: Universitas Jenderal Soedirman | AB42: =UPPER(AA42) -> UNIVERSITAS JENDERAL SOEDIRMAN
A43: Pegawai Swasta | D43: Indomarco Prismatama | H43: Perempuan | I43: =UPPER(H43) -> PEREMPUAN | R43: 42,Ekuador,Amerika Selatan | S43: =IFERROR(__xludf.DUMMYFUNCTION("SPLIT(R43,"","")"),42.0) -> 42 | T43: =IFERROR(__xludf.DUMMYFUNCTION("""COMPUTED_VALUE"""),"Ekuador") -> Ekuador | U43: =IFERROR(__xludf.DUMMYFUNCTION("""COMPUTED_VALUE"""),"Amerika Selatan") -> Amerika Selatan | AA43: Universitas Katolik Indonesia Atma Jaya | AB43: =UPPER(AA43) -> UNIVERSITAS KATOLIK INDONESIA ATMA JAYA
A44: BUMN/Pemerintahan(PNS) | D44: Kementerian PUPR | H44: Laki-laki | I44: =UPPER(H44) -> LAKI-LAKI | R44: 43,El Salvador,Amerika Utara | S44: =IFERROR(__xludf.DUMMYFUNCTION("SPLIT(R44,"","")"),43.0) -> 43 | T44: =IFERROR(__xludf.DUMMYFUNCTION("""COMPUTED_VALUE"""),"El Salvador") -> El Salvador | U44: =IFERROR(__xludf.DUMMYFUNCTION("""COMPUTED_VALUE"""),"Amerika Utara") -> Amerika Utara | AA44: Universitas Katolik Parahyangan | AB44: =UPPER(AA44) -> UNIVERSITAS KATOLIK PARAHYANGAN
A45: Organisasi Internasional | D45: ASEAN Secretariat | H45: Perempuan | I45: =UPPER(H45) -> PEREMPUAN | R45: 44,Eritrea,Afrika | S45: =IFERROR(__xludf.DUMMYFUNCTION("SPLIT(R45,"","")"),44.0) -> 44 | T45: =IFERROR(__xludf.DUMMYFUNCTION("""COMPUTED_VALUE"""),"Eritrea") -> Eritrea | U45: =IFERROR(__xludf.DUMMYFUNCTION("""COMPUTED_VALUE"""),"Afrika") -> Afrika | AA45: Universitas Katolik Soegijapranata | AB45: =UPPER(AA45) -> UNIVERSITAS KATOLIK SOEGIJAPRANATA
A46: Mahasiswa | D46: Belum Bekerja | H46: Laki-laki | I46: =UPPER(H46) -> LAKI-LAKI | R46: 45,Estonia,Eropa | S46: =IFERROR(__xludf.DUMMYFUNCTION("SPLIT(R46,"","")"),45.0) -> 45 | T46: =IFERROR(__xludf.DUMMYFUNCTION("""COMPUTED_VALUE"""),"Estonia") -> Estonia | U46: =IFERROR(__xludf.DUMMYFUNCTION("""COMPUTED_VALUE"""),"Eropa") -> Eropa | AA46: Universitas Katolik Widya Mandala Surabaya | AB46: =UPPER(AA46) -> UNIVERSITAS KATOLIK WIDYA MANDALA SURABAYA
A47: Wiraswasta | D47: SMAS K ST ARNOLDUS MUKUN | H47: Perempuan | I47: =UPPER(H47) -> PEREMPUAN | R47: 46,Eswatini,Afrika | S47: =IFERROR(__xludf.DUMMYFUNCTION("SPLIT(R47,"","")"),46.0) -> 46 | T47: =IFERROR(__xludf.DUMMYFUNCTION("""COMPUTED_VALUE"""),"Eswatini") -> Eswatini | U47: =IFERROR(__xludf.DUMMYFUNCTION("""COMPUTED_VALUE"""),"Afrika") -> Afrika | AA47: Universitas Khairun | AB47: =UPPER(AA47) -> UNIVERSITAS KHAIRUN
A48: Mahasiswa | D48: Institut Pertanian Bogor | H48: Laki-laki | I48: =UPPER(H48) -> LAKI-LAKI | R48: 47,Ethiopia,Afrika | S48: =IFERROR(__xludf.DUMMYFUNCTION("SPLIT(R48,"","")"),47.0) -> 47 | T48: =IFERROR(__xludf.DUMMYFUNCTION("""COMPUTED_VALUE"""),"Ethiopia") -> Ethiopia | U48: =IFERROR(__xludf.DUMMYFUNCTION("""COMPUTED_VALUE"""),"Afrika") -> Afrika | AA48: Universitas Kristen Duta Wacana | AB48: =UPPER(AA48) -> UNIVERSITAS KRISTEN DUTA WACANA
A49: Pegawai Swasta | D49: PT Paragon Technology and Innovation | H49: Laki-laki | I49: =UPPER(H49) -> LAKI-LAKI | R49: 48,Fiji,Oceania | S49: =IFERROR(__xludf.DUMMYFUNCTION("SPLIT(R49,"","")"),48.0) -> 48 | T49: =IFERROR(__xludf.DUMMYFUNCTION("""COMPUTED_VALUE"""),"Fiji") -> Fiji | U49: =IFERROR(__xludf.DUMMYFUNCTION("""COMPUTED_VALUE"""),"Oceania") -> Oceania | AA49: Universitas Kristen Maranatha | AB49: =UPPER(AA49) -> UNIVERSITAS KRISTEN MARANATHA
A50: Asisten Dosen | D50: Universitas Papua | H50: Laki-laki | I50: =UPPER(H50) -> LAKI-LAKI | R50: 49,Filipina,Asia | S50: =IFERROR(__xludf.DUMMYFUNCTION("SPLIT(R50,"","")"),49.0) -> 49 | T50: =IFERROR(__xludf.DUMMYFUNCTION("""COMPUTED_VALUE"""),"Filipina") -> Filipina | U50: =IFERROR(__xludf.DUMMYFUNCTION("""COMPUTED_VALUE"""),"Asia") -> Asia | AA50: Universitas Kristen Papua | AB50: =UPPER(AA50) -> UNIVERSITAS KRISTEN PAPUA
A51: Mahasiswa | D51: Belum Bekerja | H51: Perempuan | I51: =UPPER(H51) -> PEREMPUAN | R51: 50,Finlandia,Eropa | S51: =IFERROR(__xludf.DUMMYFUNCTION("SPLIT(R51,"","")"),50.0) -> 50 | T51: =IFERROR(__xludf.DUMMYFUNCTION("""COMPUTED_VALUE"""),"Finlandia") -> Finlandia | U51: =IFERROR(__xludf.DUMMYFUNCTION("""COMPUTED_VALUE"""),"Eropa") -> Eropa | AA51: Universitas Kristen Satya Wacana | AB51: =UPPER(AA51) -> UNIVERSITAS KRISTEN SATYA WACANA
A52: Profesional | D52: Deloitte | H52: Laki-laki | I52: =UPPER(H52) -> LAKI-LAKI | R52: 51,Gabon,Afrika | S52: =IFERROR(__xludf.DUMMYFUNCTION("SPLIT(R52,"","")"),51.0) -> 51 | T52: =IFERROR(__xludf.DUMMYFUNCTION("""COMPUTED_VALUE"""),"Gabon") -> Gabon | U52: =IFERROR(__xludf.DUMMYFUNCTION("""COMPUTED_VALUE"""),"Afrika") -> Afrika | AA52: Universitas Kristen Wira Wacana Sumba | AB52: =UPPER(AA52) -> UNIVERSITAS KRISTEN WIRA WACANA SUMBA
A53: Mahasiswa | D53: Belum Bekerja | H53: Perempuan | I53: =UPPER(H53) -> PEREMPUAN | R53: 52,Gambia,Afrika | S53: =IFERROR(__xludf.DUMMYFUNCTION("SPLIT(R53,"","")"),52.0) -> 52 | T53: =IFERROR(__xludf.DUMMYFUNCTION("""COMPUTED_VALUE"""),"Gambia") -> Gambia | U53: =IFERROR(__xludf.DUMMYFUNCTION("""COMPUTED_VALUE"""),"Afrika") -> Afrika | AA53: Universitas Lambung Mangkurat | AB53: =UPPER(AA53) -> UNIVERSITAS LAMBUNG MANGKURAT
A54: Wiraswasta | D54: Rambee.co | H54: Perempuan | I54: =UPPER(H54) -> PEREMPUAN | R54: 53,Georgia,Asia | S54: =IFERROR(__xludf.DUMMYFUNCTION("SPLIT(R54,"","")"),53.0) -> 53 | T54: =IFERROR(__xludf.DUMMYFUNCTION("""COMPUTED_VALUE"""),"Georgia") -> Georgia | U54: =IFERROR(__xludf.DUMMYFUNCTION("""COMPUTED_VALUE"""),"Asia") -> Asia | AA54: Universitas Lampung | AB54: =UPPER(AA54) -> UNIVERSITAS LAMPUNG
A55: Pegawai Swasta | D55: Procter & Gamble Indonesia | H55: Perempuan | I55: =UPPER(H55) -> PEREMPUAN | R55: 54,Ghana,Afrika | S55: =IFERROR(__xludf.DUMMYFUNCTION("SPLIT(R55,"","")"),54.0) -> 54 | T55: =IFERROR(__xludf.DUMMYFUNCTION("""COMPUTED_VALUE"""),"Ghana") -> Ghana | U55: =IFERROR(__xludf.DUMMYFUNCTION("""COMPUTED_VALUE"""),"Afrika") -> Afrika | AA55: Universitas Ma Chung | AB55: =UPPER(AA55) -> UNIVERSITAS MA CHUNG
A56: Pegawai Swasta | D56: PT. Sumber Alfaria Trijaya | H56: Laki-laki | I56: =UPPER(H56) -> LAKI-LAKI | R56: 55,Grenada,Amerika Utara | S56: =IFERROR(__xludf.DUMMYFUNCTION("SPLIT(R56,"","")"),55.0) -> 55 | T56: =IFERROR(__xludf.DUMMYFUNCTION("""COMPUTED_VALUE"""),"Grenada") -> Grenada | U56: =IFERROR(__xludf.DUMMYFUNCTION("""COMPUTED_VALUE"""),"Amerika Utara") -> Amerika Utara | AA56: Universitas Mataram | AB56: =UPPER(AA56) -> UNIVERSITAS MATARAM
A57: Belum Bekerja | D57: Belum Bekerja | H57: Laki-laki | I57: =UPPER(H57) -> LAKI-LAKI | R57: 56,Guatemala,Amerika Utara | S57: =IFERROR(__xludf.DUMMYFUNCTION("SPLIT(R57,"","")"),56.0) -> 56 | T57: =IFERROR(__xludf.DUMMYFUNCTION("""COMPUTED_VALUE"""),"Guatemala") -> Guatemala | U57: =IFERROR(__xludf.DUMMYFUNCTION("""COMPUTED_VALUE"""),"Amerika Utara") -> Amerika Utara | AA57: Universitas Merdeka | AB57: =UPPER(AA57) -> UNIVERSITAS MERDEKA
A58: Pegawai Swasta | D58: PT. Sebastian Citra Indonesia | H58: Perempuan | I58: =UPPER(H58) -> PEREMPUAN | R58: 57,Guinea,Afrika | S58: =IFERROR(__xludf.DUMMYFUNCTION("SPLIT(R58,"","")"),57.0) -> 57 | T58: =IFERROR(__xludf.DUMMYFUNCTION("""COMPUTED_VALUE"""),"Guinea") -> Guinea | U58: =IFERROR(__xludf.DUMMYFUNCTION("""COMPUTED_VALUE"""),"Afrika") -> Afrika | AA58: Universitas Muhammadiyah Jember | AB58: =UPPER(AA58) -> UNIVERSITAS MUHAMMADIYAH JEMBER
A59: Pegawai Swasta | D59: PT KONE INDO ELEVATOR | H59: Laki-laki | I59: =UPPER(H59) -> LAKI-LAKI | R59: 58,Guinea-Bissau,Afrika | S59: =IFERROR(__xludf.DUMMYFUNCTION("SPLIT(R59,"","")"),58.0) -> 58 | T59: =IFERROR(__xludf.DUMMYFUNCTION("""COMPUTED_VALUE"""),"Guinea-Bissau") -> Guinea-Bissau | U59: =IFERROR(__xludf.DUMMYFUNCTION("""COMPUTED_VALUE"""),"Afrika") -> Afrika | AA59: Universitas Muhammadiyah Kudus | AB59: =UPPER(AA59) -> UNIVERSITAS MUHAMMADIYAH KUDUS
A60: Pegawai Swasta | D60: PT Astra International | H60: Perempuan | I60: =UPPER(H60) -> PEREMPUAN | R60: 59,Guinea Khatulistiwa,Afrika | S60: =IFERROR(__xludf.DUMMYFUNCTION("SPLIT(R60,"","")"),59.0) -> 59 | T60: =IFERROR(__xludf.DUMMYFUNCTION("""COMPUTED_VALUE"""),"Guinea Khatulistiwa") -> Guinea Khatulistiwa | U60: =IFERROR(__xludf.DUMMYFUNCTION("""COMPUTED_VALUE"""),"Afrika") -> Afrika | AA60: Universitas Muhammadiyah Malang | AB60: =UPPER(AA60) -> UNIVERSITAS MUHAMMADIYAH MALANG
A61: Pegawai Swasta | D61: BCA | H61: Laki-laki | I61: =UPPER(H61) -> LAKI-LAKI | R61: 60,Guyana,Amerika Selatan | S61: =IFERROR(__xludf.DUMMYFUNCTION("SPLIT(R61,"","")"),60.0) -> 60 | T61: =IFERROR(__xludf.DUMMYFUNCTION("""COMPUTED_VALUE"""),"Guyana") -> Guyana | U61: =IFERROR(__xludf.DUMMYFUNCTION("""COMPUTED_VALUE"""),"Amerika Selatan") -> Amerika Selatan | AA61: Universitas Muria Kudus | AB61: =UPPER(AA61) -> UNIVERSITAS MURIA KUDUS
A62: Pegawai Swasta | D62: PT Pura Barutama | H62: Laki-laki | I62: =UPPER(H62) -> LAKI-LAKI | R62: 61,Haiti,Amerika Utara | S62: =IFERROR(__xludf.DUMMYFUNCTION("SPLIT(R62,"","")"),61.0) -> 61 | T62: =IFERROR(__xludf.DUMMYFUNCTION("""COMPUTED_VALUE"""),"Haiti") -> Haiti | U62: =IFERROR(__xludf.DUMMYFUNCTION("""COMPUTED_VALUE"""),"Amerika Utara") -> Amerika Utara | AA62: Universitas Musamus Merauke | AB62: =UPPER(AA62) -> UNIVERSITAS MUSAMUS MERAUKE
A63: Pegawai Swasta | D63: Mayapada Hospital Kuningan | H63: Perempuan | I63: =UPPER(H63) -> PEREMPUAN | R63: 62,Honduras,Amerika Utara | S63: =IFERROR(__xludf.DUMMYFUNCTION("SPLIT(R63,"","")"),62.0) -> 62 | T63: =IFERROR(__xludf.DUMMYFUNCTION("""COMPUTED_VALUE"""),"Honduras") -> Honduras | U63: =IFERROR(__xludf.DUMMYFUNCTION("""COMPUTED_VALUE"""),"Amerika Utara") -> Amerika Utara | AA63: Universitas Muslim Indonesia | AB63: =UPPER(AA63) -> UNIVERSITAS MUSLIM INDONESIA
A64: Belum Bekerja | D64: Belum Bekerja | H64: Laki-laki | I64: =UPPER(H64) -> LAKI-LAKI | R64: 63,Hungaria,Eropa | S64: =IFERROR(__xludf.DUMMYFUNCTION("SPLIT(R64,"","")"),63.0) -> 63 | T64: =IFERROR(__xludf.DUMMYFUNCTION("""COMPUTED_VALUE"""),"Hungaria") -> Hungaria | U64: =IFERROR(__xludf.DUMMYFUNCTION("""COMPUTED_VALUE"""),"Eropa") -> Eropa | AA64: Universitas Nahdatul Ulama | AB64: =UPPER(AA64) -> UNIVERSITAS NAHDATUL ULAMA
A65: Mahasiswa | D65: Belum Bekerja | H65: Laki-laki | I65: =UPPER(H65) -> LAKI-LAKI | R65: 64,India,Asia | S65: =IFERROR(__xludf.DUMMYFUNCTION("SPLIT(R65,"","")"),64.0) -> 64 | T65: =IFERROR(__xludf.DUMMYFUNCTION("""COMPUTED_VALUE"""),"India") -> India | U65: =IFERROR(__xludf.DUMMYFUNCTION("""COMPUTED_VALUE"""),"Asia") -> Asia | AA65: Universitas Nasional | AB65: =UPPER(AA65) -> UNIVERSITAS NASIONAL
A66: Magang | D66: PT Pupuk Kujang Cikampek | H66: Perempuan | I66: =UPPER(H66) -> PEREMPUAN | R66: 65,Indonesia,Asia | S66: =IFERROR(__xludf.DUMMYFUNCTION("SPLIT(R66,"","")"),65.0) -> 65 | T66: =IFERROR(__xludf.DUMMYFUNCTION("""COMPUTED_VALUE"""),"Indonesia") -> Indonesia | U66: =IFERROR(__xludf.DUMMYFUNCTION("""COMPUTED_VALUE"""),"Asia") -> Asia | AA66: Universitas Nasional Karangturi Semarang | AB66: =UPPER(AA66) -> UNIVERSITAS NASIONAL KARANGTURI SEMARANG
A67: Belum Bekerja | D67: Belum Bekerja | H67: Perempuan | I67: =UPPER(H67) -> PEREMPUAN | R67: 66,Irak,Asia | S67: =IFERROR(__xludf.DUMMYFUNCTION("SPLIT(R67,"","")"),66.0) -> 66 | T67: =IFERROR(__xludf.DUMMYFUNCTION("""COMPUTED_VALUE"""),"Irak") -> Irak | U67: =IFERROR(__xludf.DUMMYFUNCTION("""COMPUTED_VALUE"""),"Asia") -> Asia | AA67: Universitas Negeri Gorontalo | AB67: =UPPER(AA67) -> UNIVERSITAS NEGERI GORONTALO
A68: Pegawai Swasta | D68: PT Yili Indonesia Dairy | H68: Perempuan | I68: =UPPER(H68) -> PEREMPUAN | R68: 67,Iran,Asia | S68: =IFERROR(__xludf.DUMMYFUNCTION("SPLIT(R68,"","")"),67.0) -> 67 | T68: =IFERROR(__xludf.DUMMYFUNCTION("""COMPUTED_VALUE"""),"Iran") -> Iran | U68: =IFERROR(__xludf.DUMMYFUNCTION("""COMPUTED_VALUE"""),"Asia") -> Asia | AA68: Universitas Negeri Jakarta | AB68: =UPPER(AA68) -> UNIVERSITAS NEGERI JAKARTA
A69: Pegawai Swasta | D69: Ninja Xpress | H69: Perempuan | I69: =UPPER(H69) -> PEREMPUAN | R69: 68,Irlandia,Eropa | S69: =IFERROR(__xludf.DUMMYFUNCTION("SPLIT(R69,"","")"),68.0) -> 68 | T69: =IFERROR(__xludf.DUMMYFUNCTION("""COMPUTED_VALUE"""),"Irlandia") -> Irlandia | U69: =IFERROR(__xludf.DUMMYFUNCTION("""COMPUTED_VALUE"""),"Eropa") -> Eropa | AA69: Universitas Negeri Makassar | AB69: =UPPER(AA69) -> UNIVERSITAS NEGERI MAKASSAR
A70: Pegawai Swasta | D70: PT. Bank Digital BCA | H70: Laki-laki | I70: =UPPER(H70) -> LAKI-LAKI | R70: 69,Islandia,Eropa | S70: =IFERROR(__xludf.DUMMYFUNCTION("SPLIT(R70,"","")"),69.0) -> 69 | T70: =IFERROR(__xludf.DUMMYFUNCTION("""COMPUTED_VALUE"""),"Islandia") -> Islandia | U70: =IFERROR(__xludf.DUMMYFUNCTION("""COMPUTED_VALUE"""),"Eropa") -> Eropa | AA70: Universitas Negeri Malang | AB70: =UPPER(AA70) -> UNIVERSITAS NEGERI MALANG
A71: Pegawai Swasta | D71: PT Bank Central Asia Tbk | H71: Laki-laki | I71: =UPPER(H71) -> LAKI-LAKI | R71: 70,Israel,Asia | S71: =IFERROR(__xludf.DUMMYFUNCTION("SPLIT(R71,"","")"),70.0) -> 70 | T71: =IFERROR(__xludf.DUMMYFUNCTION("""COMPUTED_VALUE"""),"Israel") -> Israel | U71: =IFERROR(__xludf.DUMMYFUNCTION("""COMPUTED_VALUE"""),"Asia") -> Asia | AA71: Universitas Negeri Papua | AB71: =UPPER(AA71) -> UNIVERSITAS NEGERI PAPUA
A72: Pegawai Swasta | D72: GroupM Indonesia | H72: Laki-laki | I72: =UPPER(H72) -> LAKI-LAKI | R72: 71,Italia,Eropa | S72: =IFERROR(__xludf.DUMMYFUNCTION("SPLIT(R72,"","")"),71.0) -> 71 | T72: =IFERROR(__xludf.DUMMYFUNCTION("""COMPUTED_VALUE"""),"Italia") -> Italia | U72: =IFERROR(__xludf.DUMMYFUNCTION("""COMPUTED_VALUE"""),"Eropa") -> Eropa | AA72: Universitas Negeri Sebelas Maret | AB72: =UPPER(AA72) -> UNIVERSITAS NEGERI SEBELAS MARET
A73: Pegawai Swasta | D73: MSC Indonesia | H73: Laki-laki | I73: =UPPER(H73) -> LAKI-LAKI | R73: 72,Jamaika,Amerika Utara | S73: =IFERROR(__xludf.DUMMYFUNCTION("SPLIT(R73,"","")"),72.0) -> 72 | T73: =IFERROR(__xludf.DUMMYFUNCTION("""COMPUTED_VALUE"""),"Jamaika") -> Jamaika | U73: =IFERROR(__xludf.DUMMYFUNCTION("""COMPUTED_VALUE"""),"Amerika Utara") -> Amerika Utara | AA73: Universitas Negeri Semarang | AB73: =UPPER(AA73) -> UNIVERSITAS NEGERI SEMARANG
A74: Pegawai Swasta | D74: Ajari Technologies | H74: Laki-laki | I74: =UPPER(H74) -> LAKI-LAKI | R74: 73,Jepang,Asia | S74: =IFERROR(__xludf.DUMMYFUNCTION("SPLIT(R74,"","")"),73.0) -> 73 | T74: =IFERROR(__xludf.DUMMYFUNCTION("""COMPUTED_VALUE"""),"Jepang") -> Jepang | U74: =IFERROR(__xludf.DUMMYFUNCTION("""COMPUTED_VALUE"""),"Asia") -> Asia | AA74: Universitas Negeri Yogyakarta | AB74: =UPPER(AA74) -> UNIVERSITAS NEGERI YOGYAKARTA
A75: Pegawai Swasta | D75: PT. Tribhakti Inspektama | R75: 74,Jerman,Eropa | S75: =IFERROR(__xludf.DUMMYFUNCTION("SPLIT(R75,"","")"),74.0) -> 74 | T75: =IFERROR(__xludf.DUMMYFUNCTION("""COMPUTED_VALUE"""),"Jerman") -> Jerman | U75: =IFERROR(__xludf.DUMMYFUNCTION("""COMPUTED_VALUE"""),"Eropa") -> Eropa | AA75: Universitas Nusa Cendana | AB75: =UPPER(AA75) -> UNIVERSITAS NUSA CENDANA
A76: Pegawai Swasta | D76: PT MNC OTT Network | R76: 75,Kamboja,Asia | S76: =IFERROR(__xludf.DUMMYFUNCTION("SPLIT(R76,"","")"),75.0) -> 75 | T76: =IFERROR(__xludf.DUMMYFUNCTION("""COMPUTED_VALUE"""),"Kamboja") -> Kamboja | U76: =IFERROR(__xludf.DUMMYFUNCTION("""COMPUTED_VALUE"""),"Asia") -> Asia | AA76: Universitas Padjadjaran | AB76: =UPPER(AA76) -> UNIVERSITAS PADJADJARAN
A77: Auditor | D77: PricewaterhouseCoopers (PwC) Indonesia | R77: 76,Kamerun,Afrika | S77: =IFERROR(__xludf.DUMMYFUNCTION("SPLIT(R77,"","")"),76.0) -> 76 | T77: =IFERROR(__xludf.DUMMYFUNCTION("""COMPUTED_VALUE"""),"Kamerun") -> Kamerun | U77: =IFERROR(__xludf.DUMMYFUNCTION("""COMPUTED_VALUE"""),"Afrika") -> Afrika | AA77: Universitas Palangkaraya | AB77: =UPPER(AA77) -> UNIVERSITAS PALANGKARAYA
A78: BUMN/Pemerintahan(PNS) | D78: Asisten Deputi Ekonomi Digital Kementerian Koordinator Bidang Perekonomian | R78: 77,Kanada,Amerika Utara | S78: =IFERROR(__xludf.DUMMYFUNCTION("SPLIT(R78,"","")"),77.0) -> 77 | T78: =IFERROR(__xludf.DUMMYFUNCTION("""COMPUTED_VALUE"""),"Kanada") -> Kanada | U78: =IFERROR(__xludf.DUMMYFUNCTION("""COMPUTED_VALUE"""),"Amerika Utara") -> Amerika Utara | AA78: Universitas Paramadina | AB78: =UPPER(AA78) -> UNIVERSITAS PARAMADINA
A79: Pegawai Swasta | D79: PT Asahimas Chemical | R79: 78,Kazakhstan,Asia | S79: =IFERROR(__xludf.DUMMYFUNCTION("SPLIT(R79,"","")"),78.0) -> 78 | T79: =IFERROR(__xludf.DUMMYFUNCTION("""COMPUTED_VALUE"""),"Kazakhstan") -> Kazakhstan | U79: =IFERROR(__xludf.DUMMYFUNCTION("""COMPUTED_VALUE"""),"Asia") -> Asia | AA79: Universitas Pasundan | AB79: =UPPER(AA79) -> UNIVERSITAS PASUNDAN
A80: Pegawai Swasta | D80: Profindo Sekuritas | R80: 79,Kenya,Afrika | S80: =IFERROR(__xludf.DUMMYFUNCTION("SPLIT(R80,"","")"),79.0) -> 79 | T80: =IFERROR(__xludf.DUMMYFUNCTION("""COMPUTED_VALUE"""),"Kenya") -> Kenya | U80: =IFERROR(__xludf.DUMMYFUNCTION("""COMPUTED_VALUE"""),"Afrika") -> Afrika | AA80: Universitas Pattimura | AB80: =UPPER(AA80) -> UNIVERSITAS PATTIMURA
A81: Pegawai Swasta | D81: Kalbe Consumer Health | R81: 80,Kirgizstan,Asia | S81: =IFERROR(__xludf.DUMMYFUNCTION("SPLIT(R81,"","")"),80.0) -> 80 | T81: =IFERROR(__xludf.DUMMYFUNCTION("""COMPUTED_VALUE"""),"Kirgizstan") -> Kirgizstan | U81: =IFERROR(__xludf.DUMMYFUNCTION("""COMPUTED_VALUE"""),"Asia") -> Asia | AA81: Universitas Pembangunan Nasional Veteran Jawa Timur | AB81: =UPPER(AA81) -> UNIVERSITAS PEMBANGUNAN NASIONAL VETERAN JAWA TIMUR
A82: Pegawai Swasta | D82: Tunas Barutama Teknik | R82: 81,Kiribati,Oceania | S82: =IFERROR(__xludf.DUMMYFUNCTION("SPLIT(R82,"","")"),81.0) -> 81 | T82: =IFERROR(__xludf.DUMMYFUNCTION("""COMPUTED_VALUE"""),"Kiribati") -> Kiribati | U82: =IFERROR(__xludf.DUMMYFUNCTION("""COMPUTED_VALUE"""),"Oceania") -> Oceania | AA82: Universitas Pembangunan Nasional Veteran Yogyakarta | AB82: =UPPER(AA82) -> UNIVERSITAS PEMBANGUNAN NASIONAL VETERAN YOGYAKARTA
A83: Pegawai Swasta | D83: PT Perentjana Djaja | R83: 82,Kolombia,Amerika Selatan | S83: =IFERROR(__xludf.DUMMYFUNCTION("SPLIT(R83,"","")"),82.0) -> 82 | T83: =IFERROR(__xludf.DUMMYFUNCTION("""COMPUTED_VALUE"""),"Kolombia") -> Kolombia | U83: =IFERROR(__xludf.DUMMYFUNCTION("""COMPUTED_VALUE"""),"Amerika Selatan") -> Amerika Selatan | AA83: Universitas Pendidikan Indonesia | AB83: =UPPER(AA83) -> UNIVERSITAS PENDIDIKAN INDONESIA
A84: Pegawai Swasta | D84: PT. BCA | R84: 83,Komoro,Afrika | S84: =IFERROR(__xludf.DUMMYFUNCTION("SPLIT(R84,"","")"),83.0) -> 83 | T84: =IFERROR(__xludf.DUMMYFUNCTION("""COMPUTED_VALUE"""),"Komoro") -> Komoro | U84: =IFERROR(__xludf.DUMMYFUNCTION("""COMPUTED_VALUE"""),"Afrika") -> Afrika | AA84: Universitas Prof. Dr. Moestopo (Beragama) | AB84: =UPPER(AA84) -> UNIVERSITAS PROF. DR. MOESTOPO (BERAGAMA)
A85: Belum Bekerja | D85: Belum Bekerja | R85: 84,Kongo,Afrika | S85: =IFERROR(__xludf.DUMMYFUNCTION("SPLIT(R85,"","")"),84.0) -> 84 | T85: =IFERROR(__xludf.DUMMYFUNCTION("""COMPUTED_VALUE"""),"Kongo") -> Kongo | U85: =IFERROR(__xludf.DUMMYFUNCTION("""COMPUTED_VALUE"""),"Afrika") -> Afrika | AA85: Universitas Riau | AB85: =UPPER(AA85) -> UNIVERSITAS RIAU
A86: Pegawai Swasta | D86: PT Indoroti Prima Cemerlang (Indomaret Group) | R86: 85,Kongo (Republik Demokratik),Afrika | S86: =IFERROR(__xludf.DUMMYFUNCTION("SPLIT(R86,"","")"),85.0) -> 85 | T86: =IFERROR(__xludf.DUMMYFUNCTION("""COMPUTED_VALUE"""),"Kongo (Republik Demokratik)") -> Kongo (Republik Demokratik) | U86: =IFERROR(__xludf.DUMMYFUNCTION("""COMPUTED_VALUE"""),"Afrika") -> Afrika | AA86: Universitas Sam Ratulangi | AB86: =UPPER(AA86) -> UNIVERSITAS SAM RATULANGI
A87: Eksekutif & Manajemen Senior | D87: PT. Classic Fine Foods Indonesia | R87: 86,Korea Selatan,Asia | S87: =IFERROR(__xludf.DUMMYFUNCTION("SPLIT(R87,"","")"),86.0) -> 86 | T87: =IFERROR(__xludf.DUMMYFUNCTION("""COMPUTED_VALUE"""),"Korea Selatan") -> Korea Selatan | U87: =IFERROR(__xludf.DUMMYFUNCTION("""COMPUTED_VALUE"""),"Asia") -> Asia | AA87: Universitas Sanata Dharma | AB87: =UPPER(AA87) -> UNIVERSITAS SANATA DHARMA
A88: Belum Bekerja | D88: Belum Bekerja | R88: 87,Korea Utara,Asia | S88: =IFERROR(__xludf.DUMMYFUNCTION("SPLIT(R88,"","")"),87.0) -> 87 | T88: =IFERROR(__xludf.DUMMYFUNCTION("""COMPUTED_VALUE"""),"Korea Utara") -> Korea Utara | U88: =IFERROR(__xludf.DUMMYFUNCTION("""COMPUTED_VALUE"""),"Asia") -> Asia | AA88: Universitas Semarang | AB88: =UPPER(AA88) -> UNIVERSITAS SEMARANG
A89: BUMN/Pemerintahan(PNS) | D89: PT Pertamina Patra Niaga | R89: 88,Kosta Rika,Amerika Utara | S89: =IFERROR(__xludf.DUMMYFUNCTION("SPLIT(R89,"","")"),88.0) -> 88 | T89: =IFERROR(__xludf.DUMMYFUNCTION("""COMPUTED_VALUE"""),"Kosta Rika") -> Kosta Rika | U89: =IFERROR(__xludf.DUMMYFUNCTION("""COMPUTED_VALUE"""),"Amerika Utara") -> Amerika Utara | AA89: Universitas Siliwangi | AB89: =UPPER(AA89) -> UNIVERSITAS SILIWANGI
A90: Pegawai Swasta | D90: PT Alam Sutera Realty Tbk | R90: 89,Kroasia,Eropa | S90: =IFERROR(__xludf.DUMMYFUNCTION("SPLIT(R90,"","")"),89.0) -> 89 | T90: =IFERROR(__xludf.DUMMYFUNCTION("""COMPUTED_VALUE"""),"Kroasia") -> Kroasia | U90: =IFERROR(__xludf.DUMMYFUNCTION("""COMPUTED_VALUE"""),"Eropa") -> Eropa | AA90: Universitas Sriwijaya | AB90: =UPPER(AA90) -> UNIVERSITAS SRIWIJAYA
A91: BUMN/Pemerintahan(PNS) | D91: PT Pertamina Retail | R91: 90,Kuba,Amerika Utara | S91: =IFERROR(__xludf.DUMMYFUNCTION("SPLIT(R91,"","")"),90.0) -> 90 | T91: =IFERROR(__xludf.DUMMYFUNCTION("""COMPUTED_VALUE"""),"Kuba") -> Kuba | U91: =IFERROR(__xludf.DUMMYFUNCTION("""COMPUTED_VALUE"""),"Amerika Utara") -> Amerika Utara | AA91: Universitas Sulawesi Barat | AB91: =UPPER(AA91) -> UNIVERSITAS SULAWESI BARAT
A92: Belum Bekerja | D92: Belum Bekerja | R92: 91,Kuwait,Asia | S92: =IFERROR(__xludf.DUMMYFUNCTION("SPLIT(R92,"","")"),91.0) -> 91 | T92: =IFERROR(__xludf.DUMMYFUNCTION("""COMPUTED_VALUE"""),"Kuwait") -> Kuwait | U92: =IFERROR(__xludf.DUMMYFUNCTION("""COMPUTED_VALUE"""),"Asia") -> Asia | AA92: Universitas Sultan Ageng Tirtayasa | AB92: =UPPER(AA92) -> UNIVERSITAS SULTAN AGENG TIRTAYASA
A93: Pegawai Swasta | D93: Bomba Grup | R93: 92,Laos,Asia | S93: =IFERROR(__xludf.DUMMYFUNCTION("SPLIT(R93,"","")"),92.0) -> 92 | T93: =IFERROR(__xludf.DUMMYFUNCTION("""COMPUTED_VALUE"""),"Laos") -> Laos | U93: =IFERROR(__xludf.DUMMYFUNCTION("""COMPUTED_VALUE"""),"Asia") -> Asia | AA93: Universitas Sumatera Utara | AB93: =UPPER(AA93) -> UNIVERSITAS SUMATERA UTARA
A94: Pegawai Swasta | D94: PT. Islandsun Indonesia | R94: 93,Latvia,Eropa | S94: =IFERROR(__xludf.DUMMYFUNCTION("SPLIT(R94,"","")"),93.0) -> 93 | T94: =IFERROR(__xludf.DUMMYFUNCTION("""COMPUTED_VALUE"""),"Latvia") -> Latvia | U94: =IFERROR(__xludf.DUMMYFUNCTION("""COMPUTED_VALUE"""),"Eropa") -> Eropa | AA94: Universitas Surabaya | AB94: =UPPER(AA94) -> UNIVERSITAS SURABAYA
A95: Pegawai Swasta | D95: Samsung Electronics Indonesia | R95: 94,Lebanon,Asia | S95: =IFERROR(__xludf.DUMMYFUNCTION("SPLIT(R95,"","")"),94.0) -> 94 | T95: =IFERROR(__xludf.DUMMYFUNCTION("""COMPUTED_VALUE"""),"Lebanon") -> Lebanon | U95: =IFERROR(__xludf.DUMMYFUNCTION("""COMPUTED_VALUE"""),"Asia") -> Asia | AA95: Universitas Swadaya Gunung Jati | AB95: =UPPER(AA95) -> UNIVERSITAS SWADAYA GUNUNG JATI
A96: Pegawai Swasta | D96: PT. Alam Sutera tbk. | R96: 95,Lesotho,Afrika | S96: =IFERROR(__xludf.DUMMYFUNCTION("SPLIT(R96,"","")"),95.0) -> 95 | T96: =IFERROR(__xludf.DUMMYFUNCTION("""COMPUTED_VALUE"""),"Lesotho") -> Lesotho | U96: =IFERROR(__xludf.DUMMYFUNCTION("""COMPUTED_VALUE"""),"Afrika") -> Afrika | AA96: Universitas Syiah Kuala | AB96: =UPPER(AA96) -> UNIVERSITAS SYIAH KUALA
A97: Pegawai Swasta | D97: BCA | R97: 96,Liberia,Afrika | S97: =IFERROR(__xludf.DUMMYFUNCTION("SPLIT(R97,"","")"),96.0) -> 96 | T97: =IFERROR(__xludf.DUMMYFUNCTION("""COMPUTED_VALUE"""),"Liberia") -> Liberia | U97: =IFERROR(__xludf.DUMMYFUNCTION("""COMPUTED_VALUE"""),"Afrika") -> Afrika | AA97: Universitas Tadulako | AB97: =UPPER(AA97) -> UNIVERSITAS TADULAKO
A98: Belum Bekerja | D98: Belum Bekerja | R98: 97,Libya,Afrika | S98: =IFERROR(__xludf.DUMMYFUNCTION("SPLIT(R98,"","")"),97.0) -> 97 | T98: =IFERROR(__xludf.DUMMYFUNCTION("""COMPUTED_VALUE"""),"Libya") -> Libya | U98: =IFERROR(__xludf.DUMMYFUNCTION("""COMPUTED_VALUE"""),"Afrika") -> Afrika | AA98: Universitas Tanjungpura | AB98: =UPPER(AA98) -> UNIVERSITAS TANJUNGPURA
A99: BUMN/Pemerintahan(PNS) | D99: PT Pertamina Patra Niaga | R99: 98,Liechtenstein,Eropa | S99: =IFERROR(__xludf.DUMMYFUNCTION("SPLIT(R99,"","")"),98.0) -> 98 | T99: =IFERROR(__xludf.DUMMYFUNCTION("""COMPUTED_VALUE"""),"Liechtenstein") -> Liechtenstein | U99: =IFERROR(__xludf.DUMMYFUNCTION("""COMPUTED_VALUE"""),"Eropa") -> Eropa | AA99: Universitas Tarumanagara | AB99: =UPPER(AA99) -> UNIVERSITAS TARUMANAGARA
A100: Pegawai Swasta | D100: PT Swalayan Sukses Abadi (Part of PT Mitra Adiperkasa) | R100: 99,Lithuania,Eropa | S100: =IFERROR(__xludf.DUMMYFUNCTION("SPLIT(R100,"","")"),99.0) -> 99 | T100: =IFERROR(__xludf.DUMMYFUNCTION("""COMPUTED_VALUE"""),"Lithuania") -> Lithuania | U100: =IFERROR(__xludf.DUMMYFUNCTION("""COMPUTED_VALUE"""),"Eropa") -> Eropa | AA100: Universitas Trunojoyo | AB100: =UPPER(AA100) -> UNIVERSITAS TRUNOJOYO
...
